{"toptags": {"tag": [{"count": 100, "name": "indie pop", "url": "https://www.last.fm/tag/indie+pop"}, {"count": 56, "name": "shoegaze", "url": "https://www.last.fm/tag/shoegaze"}, {"count": 17, "name": "ambient", "url": "https://www.last.fm/tag/ambient"}, {"count": 17, "name": "electronic", "url": "https://www.last.fm/tag/electronic"}, {"count": 8, "name": "modern dream pop", "url": "https://www.last.fm/tag/modern+dream+pop"}, {"count": 8, "name": "dream pop", "url": "https://www.last.fm/tag/dream+pop"}, {"count": 2, "name": "latin", "url": "https://www.last.fm/tag/latin"}, {"count": 1, "name": "japan", "url": "https://www.last.fm/tag/japan"}, {"count": 1, "name": "alternative", "url": "https://www.last.fm/tag/alternative"}, {"count": 1, "name": "alternative rock", "url": "https://www.last.fm/tag/alternative+rock"}], "@attr": {"artist": "Harmless"}}}