{"toptags": {"tag": [{"count": 100, "name": "brazilian", "url": "https://www.last.fm/tag/brazilian"}, {"count": 100, "name": "pop", "url": "https://www.last.fm/tag/pop"}, {"count": 66, "name": "nordeste", "url": "https://www.last.fm/tag/nordeste"}, {"count": 66, "name": "Forro", "url": "https://www.last.fm/tag/Forro"}, {"count": 8, "name": "brazil", "url": "https://www.last.fm/tag/brazil"}, {"count": 8, "name": "lixo", "url": "https://www.last.fm/tag/lixo"}, {"count": 8, "name": "corno", "url": "https://www.last.fm/tag/corno"}, {"count": 2, "name": "piseiro", "url": "https://www.last.fm/tag/piseiro"}, {"count": 2, "name": "forro eletronico", "url": "https://www.last.fm/tag/forro+eletronico"}, {"count": 2, "name": "fezes", "url": "https://www.last.fm/tag/fezes"}], "@attr": {"artist": "Nattan"}}}