{"toptags": {"tag": [{"count": 100, "name": "boys planet", "url": "https://www.last.fm/tag/boys+planet"}, {"count": 44, "name": "pop", "url": "https://www.last.fm/tag/pop"}, {"count": 29, "name": "Korean", "url": "https://www.last.fm/tag/Korean"}, {"count": 7, "name": "k-pop", "url": "https://www.last.fm/tag/k-pop"}, {"count": 4, "name": "Kpop", "url": "https://www.last.fm/tag/Kpop"}, {"count": 4, "name": "bubblegum pop", "url": "https://www.last.fm/tag/bubblegum+pop"}, {"count": 4, "name": "boybands", "url": "https://www.last.fm/tag/boybands"}, {"count": 1, "name": "2023", "url": "https://www.last.fm/tag/2023"}, {"count": 1, "name": "matthew do luc", "url": "https://www.last.fm/tag/matthew+do+luc"}], "@attr": {"artist": "Say Yes!"}}}