{"toptags": {"tag": [{"count": 100, "name": "Hip-Hop", "url": "https://www.last.fm/tag/Hip-Hop"}, {"count": 86, "name": "finnish", "url": "https://www.last.fm/tag/finnish"}, {"count": 47, "name": "Suomirap", "url": "https://www.last.fm/tag/Suomirap"}, {"count": 41, "name": "rap", "url": "https://www.last.fm/tag/rap"}, {"count": 12, "name": "Suomi Hip-hop", "url": "https://www.last.fm/tag/Suomi+Hip-hop"}, {"count": 6, "name": "Komia riimi", "url": "https://www.last.fm/tag/Komia+riimi"}, {"count": 6, "name": "monsp records", "url": "https://www.last.fm/tag/monsp+records"}, {"count": 1, "name": "suomihoppi", "url": "https://www.last.fm/tag/suomihoppi"}, {"count": 1, "name": "underground hip-hop", "url": "https://www.last.fm/tag/underground+hip-hop"}, {"count": 1, "name": "hip hop", "url": "https://www.last.fm/tag/hip+hop"}], "@attr": {"artist": "Huge L"}}}