{"toptags": {"tag": [{"count": 100, "name": "Hip-Hop", "url": "https://www.last.fm/tag/Hip-Hop"}, {"count": 91, "name": "rap", "url": "https://www.last.fm/tag/rap"}, {"count": 39, "name": "better than selena gomez", "url": "https://www.last.fm/tag/better+than+selena+gomez"}, {"count": 36, "name": "urban", "url": "https://www.last.fm/tag/urban"}, {"count": 15, "name": "female rapper", "url": "https://www.last.fm/tag/female+rapper"}, {"count": 7, "name": "trap", "url": "https://www.last.fm/tag/trap"}, {"count": 4, "name": "american", "url": "https://www.last.fm/tag/american"}, {"count": 1, "name": "female vocalists", "url": "https://www.last.fm/tag/female+vocalists"}, {"count": 1, "name": "nicki minaj", "url": "https://www.last.fm/tag/nicki+minaj"}, {"count": 1, "name": "USA", "url": "https://www.last.fm/tag/USA"}], "@attr": {"artist": "Saweetie"}}}