{"tracks": {"track": [{"name": "my boy", "duration": "170", "playcount": "7496165", "listeners": "772910", "mbid": "8a3c461b-845d-49ba-9df2-0f03d1a233ff", "url": "https://www.last.fm/music/Billie+Eilish/_/my+boy", "streamable": {"#text": "0", "fulltrack": "0"}, "artist": {"name": "Billie Eilish", "mbid": "f4abc0b5-3f7a-4eff-8f78-ac078dbce533", "url": "https://www.last.fm/music/Billie+Eilish"}, "image": [{"#text": "https://lastfm.freetls.fastly.net/i/u/34s/2a96cbd8b46e442fc41c2b86b821562f.png", "size": "small"}, {"#text": "https://lastfm.freetls.fastly.net/i/u/64s/2a96cbd8b46e442fc41c2b86b821562f.png", "size": "medium"}, {"#text": "https://lastfm.freetls.fastly.net/i/u/174s/2a96cbd8b46e442fc41c2b86b821562f.png", "size": "large"}, {"#text": "https://lastfm.freetls.fastly.net/i/u/300x300/2a96cbd8b46e442fc41c2b86b821562f.png", "size": "extralarge"}]}, {"name": "eASY", "duration": "106", "playcount": "717699", "listeners": "46760", "url": "https://www.last.fm/music/HAZBIN+HOTEL/_/eASY", "streamable": {"#text": "0", "fulltrack": "0"}, "artist": {"name": "HAZBIN HOTEL", "url": "https://www.last.fm/music/HAZBIN+HOTEL"}, "image": [{"#text": "https://lastfm.freetls.fastly.net/i/u/34s/2a96cbd8b46e442fc41c2b86b821562f.png", "size": "small"}, {"#text": "https://lastfm.freetls.fastly.net/i/u/64s/2a96cbd8b46e442fc41c2b86b821562f.png", "size": "medium"}, {"#text": "https://lastfm.freetls.fastly.net/i/u/174s/2a96cbd8b46e442fc41c2b86b821562f.png", "size": "large"}, {"#text": "https://lastfm.freetls.fastly.net/i/u/300x300/2a96cbd8b46e442fc41c2b86b821562f.png", "size": "extralarge"}]}, {"name": "Leaf", "duration": "154", "playcount": "2474992", "listeners": "259406", "mbid": "04482970-01a1-3673-9bce-a8365928b7c9", "url": "https://www.last.fm/music/Title+Fight/_/Leaf", "streamable": {"#text": "0", "fulltrack": "0"}, "artist": {"name": "Title Fight", "mbid": "1154d345-8061-4d04-a52a-6214288523ac", "url": "https://www.last.fm/music/Title+Fight"}, "image": [{"#text": "https://lastfm.freetls.fastly.net/i/u/34s/2a96cbd8b46e442fc41c2b86b821562f.png", "size": "small"}, {"#text": "https://lastfm.freetls.fastly.net/i/u/64s/2a96cbd8b46e442fc41c2b86b821562f.png", "size": "medium"}, {"#text": "https://lastfm.freetls.fastly.net/i/u/174s/2a96cbd8b46e442fc41c2b86b821562f.png", "size": "large"}, {"#text": "https://lastfm.freetls.fastly.net/i/u/300x300/2a96cbd8b46e442fc41c2b86b821562f.png", "size": "extralarge"}]}, {"name": "30 Hours", "duration": "247", "playcount": "6983132", "listeners": "596427", "mbid": "e71b3d29-cc25-47c3-9f0d-ae054a3d9e39", "url": "https://www.last.fm/music/Kanye+West/_/30+Hours", "streamable": {"#text": "0", "fulltrack": "0"}, "artist": {"name": "Kanye West", "url": "https://www.last.fm/music/Kanye+West"}, "image": [{"#text": "https://lastfm.freetls.fastly.net/i/u/34s/2a96cbd8b46e442fc41c2b86b821562f.png", "size": "small"}, {"#text": "https://lastfm.freetls.fastly.net/i/u/64s/2a96cbd8b46e442fc41c2b86b821562f.png", "size": "medium"}, {"#text": "https://lastfm.freetls.fastly.net/i/u/174s/2a96cbd8b46e442fc41c2b86b821562f.png", "size": "large"}, {"#text": "https://lastfm.freetls.fastly.net/i/u/300x300/2a96cbd8b46e442fc41c2b86b821562f.png", "size": "extralarge"}]}, {"name": "What You Saying", "duration": "131", "playcount": "76357", "listeners": "16220", "mbid": "ec0a778c-979a-453b-ad2c-87169f497dca", "url": "https://www.last.fm/music/Lil+Uzi+Vert/_/What+You+Saying", "streamable": {"#text": "0", "fulltrack": "0"}, "artist": {"name": "Lil Uzi Vert", "mbid": "8837b875-3689-4646-b3fd-d8b53815c7a8", "url": "https://www.last.fm/music/Lil+Uzi+Vert"}, "image": [{"#text": "https://lastfm.freetls.fastly.net/i/u/34s/2a96cbd8b46e442fc41c2b86b821562f.png", "size": "small"}, {"#text": "https://lastfm.freetls.fastly.net/i/u/64s/2a96cbd8b46e442fc41c2b86b821562f.png", "size": "medium"}, {"#text": "https://lastfm.freetls.fastly.net/i/u/174s/2a96cbd8b46e442fc41c2b86b821562f.png", "size": "large"}, {"#text": "https://lastfm.freetls.fastly.net/i/u/300x300/2a96cbd8b46e442fc41c2b86b821562f.png", "size": "extralarge"}]}, {"name": "Quiet, The Winter Harbor", "duration": "255", "playcount": "2709593", "listeners": "303519", "mbid": "6a6ac233-e278-434c-b29f-604601d56d9e", "url": "https://www.last.fm/music/Mazzy+Star/_/Quiet,+The+Winter+Harbor", "streamable": {"#text": "0", "fulltrack": "0"}, "artist": {"name": "Mazzy Star", "mbid": "c48d4327-8122-4286-af66-05e1ee6ac4d8", "url": "https://www.last.fm/music/Mazzy+Star"}, "image": [{"#text": "https://lastfm.freetls.fastly.net/i/u/34s/2a96cbd8b46e442fc41c2b86b821562f.png", "size": "small"}, {"#text": "https://lastfm.freetls.fastly.net/i/u/64s/2a96cbd8b46e442fc41c2b86b821562f.png", "size": "medium"}, {"#text": "https://lastfm.freetls.fastly.net/i/u/174s/2a96cbd8b46e442fc41c2b86b821562f.png", "size": "large"}, {"#text": "https://lastfm.freetls.fastly.net/i/u/300x300/2a96cbd8b46e442fc41c2b86b821562f.png", "size": "extralarge"}]}, {"name": "GIRL HELL 1999", "duration": "145", "playcount": "2910359", "listeners": "146066", "mbid": "38c9d6c4-11ba-45dd-9ca6-6b9f756478e4", "url": "https://www.last.fm/music/femtanyl/_/GIRL+HELL+1999", "streamable": {"#text": "0", "fulltrack": "0"}, "artist": {"name": "femtanyl", "mbid": "eb3c021d-e056-42d6-8fad-064205a90527", "url": "https://www.last.fm/music/femtanyl"}, "image": [{"#text": "https://lastfm.freetls.fastly.net/i/u/34s/2a96cbd8b46e442fc41c2b86b821562f.png", "size": "small"}, {"#text": "https://lastfm.freetls.fastly.net/i/u/64s/2a96cbd8b46e442fc41c2b86b821562f.png", "size": "medium"}, {"#text": "https://lastfm.freetls.fastly.net/i/u/174s/2a96cbd8b46e442fc41c2b86b821562f.png", "size": "large"}, {"#text": "https://lastfm.freetls.fastly.net/i/u/300x300/2a96cbd8b46e442fc41c2b86b821562f.png", "size": "extralarge"}]}, {"name": "Sorry", "duration": "156", "playcount": "4133834", "listeners": "345369", "mbid": "64a1fdfe-78fd-4954-8d49-1b399e6f305d", "url": "https://www.last.fm/music/Alex+G/_/Sorry", "streamable": {"#text": "0", "fulltrack": "0"}, "artist": {"name": "Alex G", "mbid": "7df4c4de-3181-4a69-bd36-9d663970cebb", "url": "https://www.last.fm/music/Alex+G"}, "image": [{"#text": "https://lastfm.freetls.fastly.net/i/u/34s/2a96cbd8b46e442fc41c2b86b821562f.png", "size": "small"}, {"#text": "https://lastfm.freetls.fastly.net/i/u/64s/2a96cbd8b46e442fc41c2b86b821562f.png", "size": "medium"}, {"#text": "https://lastfm.freetls.fastly.net/i/u/174s/2a96cbd8b46e442fc41c2b86b821562f.png", "size": "large"}, {"#text": "https://lastfm.freetls.fastly.net/i/u/300x300/2a96cbd8b46e442fc41c2b86b821562f.png", "size": "extralarge"}]}, {"name": "I'M THAT GIRL", "duration": "0", "playcount": "9864728", "listeners": "536792", "mbid": "8ff568b6-aaa9-4c9f-afe3-2e3aba710929", "url": "https://www.last.fm/music/Beyonc%C3%A9/_/I%27M+THAT+GIRL", "streamable": {"#text": "0", "fulltrack": "0"}, "artist": {"name": "Beyonc\u00e9", "mbid": "859d0860-d480-4efd-970c-c05d5f1776b8", "url": "https://www.last.fm/music/Beyonc%C3%A9"}, "image": [{"#text": "https://lastfm.freetls.fastly.net/i/u/34s/2a96cbd8b46e442fc41c2b86b821562f.png", "size": "small"}, {"#text": "https://lastfm.freetls.fastly.net/i/u/64s/2a96cbd8b46e442fc41c2b86b821562f.png", "size": "medium"}, {"#text": "https://lastfm.freetls.fastly.net/i/u/174s/2a96cbd8b46e442fc41c2b86b821562f.png", "size": "large"}, {"#text": "https://lastfm.freetls.fastly.net/i/u/300x300/2a96cbd8b46e442fc41c2b86b821562f.png", "size": "extralarge"}]}, {"name": "Right Here", "duration": "235", "playcount": "4522208", "listeners": "361501", "mbid": "05687b80-e425-43cc-a15b-63179c2ec35c", "url": "https://www.last.fm/music/Chase+Atlantic/_/Right+Here", "streamable": {"#text": "0", "fulltrack": "0"}, "artist": {"name": "Chase Atlantic", "mbid": "ecab255c-3af3-4154-87ec-2685041ce297", "url": "https://www.last.fm/music/Chase+Atlantic"}, "image": [{"#text": "https://lastfm.freetls.fastly.net/i/u/34s/2a96cbd8b46e442fc41c2b86b821562f.png", "size": "small"}, {"#text": "https://lastfm.freetls.fastly.net/i/u/64s/2a96cbd8b46e442fc41c2b86b821562f.png", "size": "medium"}, {"#text": "https://lastfm.freetls.fastly.net/i/u/174s/2a96cbd8b46e442fc41c2b86b821562f.png", "size": "large"}, {"#text": "https://lastfm.freetls.fastly.net/i/u/300x300/2a96cbd8b46e442fc41c2b86b821562f.png", "size": "extralarge"}]}, {"name": "R\u00e4t", "duration": "194", "playcount": "4926066", "listeners": "469907", "mbid": "3d5e680a-2ebe-402c-a0fd-afc5350caece", "url": "https://www.last.fm/music/Penelope+Scott/_/R%C3%A4t", "streamable": {"#text": "0", "fulltrack": "0"}, "artist": {"name": "Penelope Scott", "mbid": "e04f63b1-997c-4759-af02-2d3324741479", "url": "https://www.last.fm/music/Penelope+Scott"}, "image": [{"#text": "https://lastfm.freetls.fastly.net/i/u/34s/2a96cbd8b46e442fc41c2b86b821562f.png", "size": "small"}, {"#text": "https://lastfm.freetls.fastly.net/i/u/64s/2a96cbd8b46e442fc41c2b86b821562f.png", "size": "medium"}, {"#text": "https://lastfm.freetls.fastly.net/i/u/174s/2a96cbd8b46e442fc41c2b86b821562f.png", "size": "large"}, {"#text": "https://lastfm.freetls.fastly.net/i/u/300x300/2a96cbd8b46e442fc41c2b86b821562f.png", "size": "extralarge"}]}, {"name": "Kyoto", "duration": "270", "playcount": "6647061", "listeners": "380317", "mbid": "c94c435c-7801-421c-8654-ffdc7948893f", "url": "https://www.last.fm/music/Yung+Lean/_/Kyoto", "streamable": {"#text": "0", "fulltrack": "0"}, "artist": {"name": "Yung Lean", "mbid": "757ed661-fbad-4e45-b1cd-a6b09f06f54a", "url": "https://www.last.fm/music/Yung+Lean"}, "image": [{"#text": "https://lastfm.freetls.fastly.net/i/u/34s/2a96cbd8b46e442fc41c2b86b821562f.png", "size": "small"}, {"#text": "https://lastfm.freetls.fastly.net/i/u/64s/2a96cbd8b46e442fc41c2b86b821562f.png", "size": "medium"}, {"#text": "https://lastfm.freetls.fastly.net/i/u/174s/2a96cbd8b46e442fc41c2b86b821562f.png", "size": "large"}, {"#text": "https://lastfm.freetls.fastly.net/i/u/300x300/2a96cbd8b46e442fc41c2b86b821562f.png", "size": "extralarge"}]}, {"name": "All Star", "duration": "200", "playcount": "10423017", "listeners": "1562735", "mbid": "67c86035-7b1b-4400-9b65-3e5747a1e78f", "url": "https://www.last.fm/music/Smash+Mouth/_/All+Star", "streamable": {"#text": "0", "fulltrack": "0"}, "artist": {"name": "Smash Mouth", "mbid": "944e1036-8a03-4611-8aa0-31515a05c848", "url": "https://www.last.fm/music/Smash+Mouth"}, "image": [{"#text": "https://lastfm.freetls.fastly.net/i/u/34s/2a96cbd8b46e442fc41c2b86b821562f.png", "size": "small"}, {"#text": "https://lastfm.freetls.fastly.net/i/u/64s/2a96cbd8b46e442fc41c2b86b821562f.png", "size": "medium"}, {"#text": "https://lastfm.freetls.fastly.net/i/u/174s/2a96cbd8b46e442fc41c2b86b821562f.png", "size": "large"}, {"#text": "https://lastfm.freetls.fastly.net/i/u/300x300/2a96cbd8b46e442fc41c2b86b821562f.png", "size": "extralarge"}]}, {"name": "Better Than Revenge", "duration": "382", "playcount": "9480340", "listeners": "677528", "mbid": "01915ca7-735f-4494-bde9-d1bcf0ec7c1b", "url": "https://www.last.fm/music/Taylor+Swift/_/Better+Than+Revenge", "streamable": {"#text": "0", "fulltrack": "0"}, "artist": {"name": "Taylor Swift", "mbid": "20244d07-534f-4eff-b4d4-930878889970", "url": "https://www.last.fm/music/Taylor+Swift"}, "image": [{"#text": "https://lastfm.freetls.fastly.net/i/u/34s/2a96cbd8b46e442fc41c2b86b821562f.png", "size": "small"}, {"#text": "https://lastfm.freetls.fastly.net/i/u/64s/2a96cbd8b46e442fc41c2b86b821562f.png", "size": "medium"}, {"#text": "https://lastfm.freetls.fastly.net/i/u/174s/2a96cbd8b46e442fc41c2b86b821562f.png", "size": "large"}, {"#text": "https://lastfm.freetls.fastly.net/i/u/300x300/2a96cbd8b46e442fc41c2b86b821562f.png", "size": "extralarge"}]}, {"name": "Sorry Not Sorry", "duration": "206", "playcount": "8110263", "listeners": "656730", "mbid": "3ca54337-e917-467e-b6f3-4abe0b94febc", "url": "https://www.last.fm/music/Tyler,+The+Creator/_/Sorry+Not+Sorry", "streamable": {"#text": "0", "fulltrack": "0"}, "artist": {"name": "Tyler, The Creator", "mbid": "f6beac20-5dfe-4d1f-ae02-0b0a740aafd6", "url": "https://www.last.fm/music/Tyler,+The+Creator"}, "image": [{"#text": "https://lastfm.freetls.fastly.net/i/u/34s/2a96cbd8b46e442fc41c2b86b821562f.png", "size": "small"}, {"#text": "https://lastfm.freetls.fastly.net/i/u/64s/2a96cbd8b46e442fc41c2b86b821562f.png", "size": "medium"}, {"#text": "https://lastfm.freetls.fastly.net/i/u/174s/2a96cbd8b46e442fc41c2b86b821562f.png", "size": "large"}, {"#text": "https://lastfm.freetls.fastly.net/i/u/300x300/2a96cbd8b46e442fc41c2b86b821562f.png", "size": "extralarge"}]}, {"name": "CSIRAC", "duration": "201", "playcount": "515027", "listeners": "81435", "mbid": "c0c73a03-5d39-411d-9c93-7ce71009c2a1", "url": "https://www.last.fm/music/Ninajirachi/_/CSIRAC", "streamable": {"#text": "0", "fulltrack": "0"}, "artist": {"name": "Ninajirachi", "mbid": "6897b46a-9236-4480-9ed7-300f6b85d62f", "url": "https://www.last.fm/music/Ninajirachi"}, "image": [{"#text": "https://lastfm.freetls.fastly.net/i/u/34s/2a96cbd8b46e442fc41c2b86b821562f.png", "size": "small"}, {"#text": "https://lastfm.freetls.fastly.net/i/u/64s/2a96cbd8b46e442fc41c2b86b821562f.png", "size": "medium"}, {"#text": "https://lastfm.freetls.fastly.net/i/u/174s/2a96cbd8b46e442fc41c2b86b821562f.png", "size": "large"}, {"#text": "https://lastfm.freetls.fastly.net/i/u/300x300/2a96cbd8b46e442fc41c2b86b821562f.png", "size": "extralarge"}]}, {"name": "Shut Up", "duration": "125", "playcount": "3167701", "listeners": "179285", "mbid": "ee6d7edd-ef35-4a17-b8ed-d257cdb3766d", "url": "https://www.last.fm/music/nettspend/_/Shut+Up", "streamable": {"#text": "0", "fulltrack": "0"}, "artist": {"name": "nettspend", "url": "https://www.last.fm/music/nettspend"}, "image": [{"#text": "https://lastfm.freetls.fastly.net/i/u/34s/2a96cbd8b46e442fc41c2b86b821562f.png", "size": "small"}, {"#text": "https://lastfm.freetls.fastly.net/i/u/64s/2a96cbd8b46e442fc41c2b86b821562f.png", "size": "medium"}, {"#text": "https://lastfm.freetls.fastly.net/i/u/174s/2a96cbd8b46e442fc41c2b86b821562f.png", "size": "large"}, {"#text": "https://lastfm.freetls.fastly.net/i/u/300x300/2a96cbd8b46e442fc41c2b86b821562f.png", "size": "extralarge"}]}, {"name": "1AM FREESTYLE", "duration": "113", "playcount": "4894572", "listeners": "359981", "url": "https://www.last.fm/music/Joji/_/1AM+FREESTYLE", "streamable": {"#text": "0", "fulltrack": "0"}, "artist": {"name": "Joji", "mbid": "74922d42-c3ec-4f7d-8a24-20da6eda6ba6", "url": "https://www.last.fm/music/Joji"}, "image": [{"#text": "https://lastfm.freetls.fastly.net/i/u/34s/2a96cbd8b46e442fc41c2b86b821562f.png", "size": "small"}, {"#text": "https://lastfm.freetls.fastly.net/i/u/64s/2a96cbd8b46e442fc41c2b86b821562f.png", "size": "medium"}, {"#text": "https://lastfm.freetls.fastly.net/i/u/174s/2a96cbd8b46e442fc41c2b86b821562f.png", "size": "large"}, {"#text": "https://lastfm.freetls.fastly.net/i/u/300x300/2a96cbd8b46e442fc41c2b86b821562f.png", "size": "extralarge"}]}, {"name": "KRYPTONITE", "duration": "182", "playcount": "3307452", "listeners": "301183", "url": "https://www.last.fm/music/Don+Toliver/_/KRYPTONITE", "streamable": {"#text": "0", "fulltrack": "0"}, "artist": {"name": "Don Toliver", "mbid": "a0723a3c-4135-438e-85c5-012712144ede", "url": "https://www.last.fm/music/Don+Toliver"}, "image": [{"#text": "https://lastfm.freetls.fastly.net/i/u/34s/2a96cbd8b46e442fc41c2b86b821562f.png", "size": "small"}, {"#text": "https://lastfm.freetls.fastly.net/i/u/64s/2a96cbd8b46e442fc41c2b86b821562f.png", "size": "medium"}, {"#text": "https://lastfm.freetls.fastly.net/i/u/174s/2a96cbd8b46e442fc41c2b86b821562f.png", "size": "large"}, {"#text": "https://lastfm.freetls.fastly.net/i/u/300x300/2a96cbd8b46e442fc41c2b86b821562f.png", "size": "extralarge"}]}, {"name": "ROLE MODEL", "duration": "261", "playcount": "5159127", "listeners": "411993", "mbid": "0278242f-5291-4035-8136-1213dbbe2414", "url": "https://www.last.fm/music/Brent+Faiyaz/_/ROLE+MODEL", "streamable": {"#text": "0", "fulltrack": "0"}, "artist": {"name": "Brent Faiyaz", "mbid": "201412c6-7ced-472b-87a9-9259ec3c07d3", "url": "https://www.last.fm/music/Brent+Faiyaz"}, "image": [{"#text": "https://lastfm.freetls.fastly.net/i/u/34s/2a96cbd8b46e442fc41c2b86b821562f.png", "size": "small"}, {"#text": "https://lastfm.freetls.fastly.net/i/u/64s/2a96cbd8b46e442fc41c2b86b821562f.png", "size": "medium"}, {"#text": "https://lastfm.freetls.fastly.net/i/u/174s/2a96cbd8b46e442fc41c2b86b821562f.png", "size": "large"}, {"#text": "https://lastfm.freetls.fastly.net/i/u/300x300/2a96cbd8b46e442fc41c2b86b821562f.png", "size": "extralarge"}]}, {"name": "Look to Windward", "duration": "466", "playcount": "2439269", "listeners": "136157", "mbid": "f1ffbd05-d86b-402f-baf3-2e6bfb54f96c", "url": "https://www.last.fm/music/Sleep+Token/_/Look+to+Windward", "streamable": {"#text": "0", "fulltrack": "0"}, "artist": {"name": "Sleep Token", "mbid": "775ad383-ac2d-479a-af9d-b561442cb749", "url": "https://www.last.fm/music/Sleep+Token"}, "image": [{"#text": "https://lastfm.freetls.fastly.net/i/u/34s/2a96cbd8b46e442fc41c2b86b821562f.png", "size": "small"}, {"#text": "https://lastfm.freetls.fastly.net/i/u/64s/2a96cbd8b46e442fc41c2b86b821562f.png", "size": "medium"}, {"#text": "https://lastfm.freetls.fastly.net/i/u/174s/2a96cbd8b46e442fc41c2b86b821562f.png", "size": "large"}, {"#text": "https://lastfm.freetls.fastly.net/i/u/300x300/2a96cbd8b46e442fc41c2b86b821562f.png", "size": "extralarge"}]}, {"name": "Niagara Falls (Foot or 2) [with Travis Scott & 21 Savage]", "duration": "207", "playcount": "8163173", "listeners": "565998", "url": "https://www.last.fm/music/Metro+Boomin/_/Niagara+Falls+(Foot+or+2)+%5Bwith+Travis+Scott+&+21+Savage%5D", "streamable": {"#text": "0", "fulltrack": "0"}, "artist": {"name": "Metro Boomin", "mbid": "59db3d82-86ea-451f-881f-dffc8ec387c9", "url": "https://www.last.fm/music/Metro+Boomin"}, "image": [{"#text": "https://lastfm.freetls.fastly.net/i/u/34s/2a96cbd8b46e442fc41c2b86b821562f.png", "size": "small"}, {"#text": "https://lastfm.freetls.fastly.net/i/u/64s/2a96cbd8b46e442fc41c2b86b821562f.png", "size": "medium"}, {"#text": "https://lastfm.freetls.fastly.net/i/u/174s/2a96cbd8b46e442fc41c2b86b821562f.png", "size": "large"}, {"#text": "https://lastfm.freetls.fastly.net/i/u/300x300/2a96cbd8b46e442fc41c2b86b821562f.png", "size": "extralarge"}]}, {"name": "Mice on Venus", "duration": "281", "playcount": "5104532", "listeners": "515529", "mbid": "19274c4d-523c-435d-8ba5-caaf45e4fd8a", "url": "https://www.last.fm/music/C418/_/Mice+on+Venus", "streamable": {"#text": "0", "fulltrack": "0"}, "artist": {"name": "C418", "mbid": "fac55e3c-d459-45ed-9f9f-f5078d3b3423", "url": "https://www.last.fm/music/C418"}, "image": [{"#text": "https://lastfm.freetls.fastly.net/i/u/34s/2a96cbd8b46e442fc41c2b86b821562f.png", "size": "small"}, {"#text": "https://lastfm.freetls.fastly.net/i/u/64s/2a96cbd8b46e442fc41c2b86b821562f.png", "size": "medium"}, {"#text": "https://lastfm.freetls.fastly.net/i/u/174s/2a96cbd8b46e442fc41c2b86b821562f.png", "size": "large"}, {"#text": "https://lastfm.freetls.fastly.net/i/u/300x300/2a96cbd8b46e442fc41c2b86b821562f.png", "size": "extralarge"}]}, {"name": "BTS Cypher PT.3 : KILLER (feat. Supreme Boi)", "duration": "268", "playcount": "2091283", "listeners": "135723", "url": "https://www.last.fm/music/BTS/_/BTS+Cypher+PT.3+:+KILLER+(feat.+Supreme+Boi)", "streamable": {"#text": "0", "fulltrack": "0"}, "artist": {"name": "BTS", "mbid": "0d79fe8e-ba27-4859-bb8c-2f255f346853", "url": "https://www.last.fm/music/BTS"}, "image": [{"#text": "https://lastfm.freetls.fastly.net/i/u/34s/2a96cbd8b46e442fc41c2b86b821562f.png", "size": "small"}, {"#text": "https://lastfm.freetls.fastly.net/i/u/64s/2a96cbd8b46e442fc41c2b86b821562f.png", "size": "medium"}, {"#text": "https://lastfm.freetls.fastly.net/i/u/174s/2a96cbd8b46e442fc41c2b86b821562f.png", "size": "large"}, {"#text": "https://lastfm.freetls.fastly.net/i/u/300x300/2a96cbd8b46e442fc41c2b86b821562f.png", "size": "extralarge"}]}, {"name": "Pharsyde (feat. Joe Fox)", "duration": "222", "playcount": "2157587", "listeners": "256184", "url": "https://www.last.fm/music/A$AP+Rocky/_/Pharsyde+(feat.+Joe+Fox)", "streamable": {"#text": "0", "fulltrack": "0"}, "artist": {"name": "A$AP Rocky", "mbid": "25b7b584-d952-4662-a8b9-dd8cdfbfeb64", "url": "https://www.last.fm/music/A$AP+Rocky"}, "image": [{"#text": "https://lastfm.freetls.fastly.net/i/u/34s/2a96cbd8b46e442fc41c2b86b821562f.png", "size": "small"}, {"#text": "https://lastfm.freetls.fastly.net/i/u/64s/2a96cbd8b46e442fc41c2b86b821562f.png", "size": "medium"}, {"#text": "https://lastfm.freetls.fastly.net/i/u/174s/2a96cbd8b46e442fc41c2b86b821562f.png", "size": "large"}, {"#text": "https://lastfm.freetls.fastly.net/i/u/300x300/2a96cbd8b46e442fc41c2b86b821562f.png", "size": "extralarge"}]}, {"name": "Ladies Room", "duration": "220", "playcount": "960349", "listeners": "159374", "mbid": "a0bd6d25-178b-4db2-b541-805608a7db60", "url": "https://www.last.fm/music/Olivia+Dean/_/Ladies+Room", "streamable": {"#text": "0", "fulltrack": "0"}, "artist": {"name": "Olivia Dean", "mbid": "15e0d608-0869-429b-898d-3d8db3ecedd5", "url": "https://www.last.fm/music/Olivia+Dean"}, "image": [{"#text": "https://lastfm.freetls.fastly.net/i/u/34s/2a96cbd8b46e442fc41c2b86b821562f.png", "size": "small"}, {"#text": "https://lastfm.freetls.fastly.net/i/u/64s/2a96cbd8b46e442fc41c2b86b821562f.png", "size": "medium"}, {"#text": "https://lastfm.freetls.fastly.net/i/u/174s/2a96cbd8b46e442fc41c2b86b821562f.png", "size": "large"}, {"#text": "https://lastfm.freetls.fastly.net/i/u/300x300/2a96cbd8b46e442fc41c2b86b821562f.png", "size": "extralarge"}]}, {"name": "Let Go", "duration": "176", "playcount": "8717001", "listeners": "699432", "mbid": "474c51a7-6dd8-4be4-95ef-4b40817e7db5", "url": "https://www.last.fm/music/Aaron+May/_/Let+Go", "streamable": {"#text": "0", "fulltrack": "0"}, "artist": {"name": "Aaron May", "mbid": "9f3225ad-e686-4538-8cbe-99406c4a4caa", "url": "https://www.last.fm/music/Aaron+May"}, "image": [{"#text": "https://lastfm.freetls.fastly.net/i/u/34s/2a96cbd8b46e442fc41c2b86b821562f.png", "size": "small"}, {"#text": "https://lastfm.freetls.fastly.net/i/u/64s/2a96cbd8b46e442fc41c2b86b821562f.png", "size": "medium"}, {"#text": "https://lastfm.freetls.fastly.net/i/u/174s/2a96cbd8b46e442fc41c2b86b821562f.png", "size": "large"}, {"#text": "https://lastfm.freetls.fastly.net/i/u/300x300/2a96cbd8b46e442fc41c2b86b821562f.png", "size": "extralarge"}]}, {"name": "light", "duration": "225", "playcount": "5987300", "listeners": "346452", "url": "https://www.last.fm/music/wave+to+earth/_/light", "streamable": {"#text": "0", "fulltrack": "0"}, "artist": {"name": "wave to earth", "mbid": "89e95aa3-bd49-4af3-9c87-0d88b2093bb0", "url": "https://www.last.fm/music/wave+to+earth"}, "image": [{"#text": "https://lastfm.freetls.fastly.net/i/u/34s/2a96cbd8b46e442fc41c2b86b821562f.png", "size": "small"}, {"#text": "https://lastfm.freetls.fastly.net/i/u/64s/2a96cbd8b46e442fc41c2b86b821562f.png", "size": "medium"}, {"#text": "https://lastfm.freetls.fastly.net/i/u/174s/2a96cbd8b46e442fc41c2b86b821562f.png", "size": "large"}, {"#text": "https://lastfm.freetls.fastly.net/i/u/300x300/2a96cbd8b46e442fc41c2b86b821562f.png", "size": "extralarge"}]}, {"name": "Silver Bells", "duration": "169", "playcount": "680492", "listeners": "263094", "url": "https://www.last.fm/music/Bing+Crosby/_/Silver+Bells", "streamable": {"#text": "0", "fulltrack": "0"}, "artist": {"name": "Bing Crosby", "mbid": "2437980f-513a-44fc-80f1-b90d9d7fcf8f", "url": "https://www.last.fm/music/Bing+Crosby"}, "image": [{"#text": "https://lastfm.freetls.fastly.net/i/u/34s/2a96cbd8b46e442fc41c2b86b821562f.png", "size": "small"}, {"#text": "https://lastfm.freetls.fastly.net/i/u/64s/2a96cbd8b46e442fc41c2b86b821562f.png", "size": "medium"}, {"#text": "https://lastfm.freetls.fastly.net/i/u/174s/2a96cbd8b46e442fc41c2b86b821562f.png", "size": "large"}, {"#text": "https://lastfm.freetls.fastly.net/i/u/300x300/2a96cbd8b46e442fc41c2b86b821562f.png", "size": "extralarge"}]}, {"name": "The Christmas Song", "duration": "195", "playcount": "867043", "listeners": "222380", "mbid": "02f3d1a3-9006-340a-b6d4-a3e12ca9cbbb", "url": "https://www.last.fm/music/Vince+Guaraldi+Trio/_/The+Christmas+Song", "streamable": {"#text": "0", "fulltrack": "0"}, "artist": {"name": "Vince Guaraldi Trio", "mbid": "744b52c8-509b-4451-abfd-a17d18d4bd1d", "url": "https://www.last.fm/music/Vince+Guaraldi+Trio"}, "image": [{"#text": "https://lastfm.freetls.fastly.net/i/u/34s/2a96cbd8b46e442fc41c2b86b821562f.png", "size": "small"}, {"#text": "https://lastfm.freetls.fastly.net/i/u/64s/2a96cbd8b46e442fc41c2b86b821562f.png", "size": "medium"}, {"#text": "https://lastfm.freetls.fastly.net/i/u/174s/2a96cbd8b46e442fc41c2b86b821562f.png", "size": "large"}, {"#text": "https://lastfm.freetls.fastly.net/i/u/300x300/2a96cbd8b46e442fc41c2b86b821562f.png", "size": "extralarge"}]}, {"name": "Armed and Dangerous", "duration": "169", "playcount": "8973188", "listeners": "552029", "mbid": "3f40f625-6908-43e3-b7ff-87300a92f666", "url": "https://www.last.fm/music/Juice+WRLD/_/Armed+and+Dangerous", "streamable": {"#text": "0", "fulltrack": "0"}, "artist": {"name": "Juice WRLD", "mbid": "4e4ebde4-0c56-4dec-844b-6c73adcdd92d", "url": "https://www.last.fm/music/Juice+WRLD"}, "image": [{"#text": "https://lastfm.freetls.fastly.net/i/u/34s/2a96cbd8b46e442fc41c2b86b821562f.png", "size": "small"}, {"#text": "https://lastfm.freetls.fastly.net/i/u/64s/2a96cbd8b46e442fc41c2b86b821562f.png", "size": "medium"}, {"#text": "https://lastfm.freetls.fastly.net/i/u/174s/2a96cbd8b46e442fc41c2b86b821562f.png", "size": "large"}, {"#text": "https://lastfm.freetls.fastly.net/i/u/300x300/2a96cbd8b46e442fc41c2b86b821562f.png", "size": "extralarge"}]}, {"name": "Invincible (feat. Daniel Caesar)", "duration": "216", "playcount": "3481562", "listeners": "374627", "url": "https://www.last.fm/music/Omar+Apollo/_/Invincible+(feat.+Daniel+Caesar)", "streamable": {"#text": "0", "fulltrack": "0"}, "artist": {"name": "Omar Apollo", "mbid": "0b966a38-5ad9-43c1-b86b-c07079523165", "url": "https://www.last.fm/music/Omar+Apollo"}, "image": [{"#text": "https://lastfm.freetls.fastly.net/i/u/34s/2a96cbd8b46e442fc41c2b86b821562f.png", "size": "small"}, {"#text": "https://lastfm.freetls.fastly.net/i/u/64s/2a96cbd8b46e442fc41c2b86b821562f.png", "size": "medium"}, {"#text": "https://lastfm.freetls.fastly.net/i/u/174s/2a96cbd8b46e442fc41c2b86b821562f.png", "size": "large"}, {"#text": "https://lastfm.freetls.fastly.net/i/u/300x300/2a96cbd8b46e442fc41c2b86b821562f.png", "size": "extralarge"}]}, {"name": "All of the Girls You Loved Before", "duration": "221", "playcount": "12374536", "listeners": "652251", "mbid": "d129c5e9-4c53-443f-b96c-30547005c821", "url": "https://www.last.fm/music/Taylor+Swift/_/All+of+the+Girls+You+Loved+Before", "streamable": {"#text": "0", "fulltrack": "0"}, "artist": {"name": "Taylor Swift", "mbid": "20244d07-534f-4eff-b4d4-930878889970", "url": "https://www.last.fm/music/Taylor+Swift"}, "image": [{"#text": "https://lastfm.freetls.fastly.net/i/u/34s/2a96cbd8b46e442fc41c2b86b821562f.png", "size": "small"}, {"#text": "https://lastfm.freetls.fastly.net/i/u/64s/2a96cbd8b46e442fc41c2b86b821562f.png", "size": "medium"}, {"#text": "https://lastfm.freetls.fastly.net/i/u/174s/2a96cbd8b46e442fc41c2b86b821562f.png", "size": "large"}, {"#text": "https://lastfm.freetls.fastly.net/i/u/300x300/2a96cbd8b46e442fc41c2b86b821562f.png", "size": "extralarge"}]}, {"name": "= (Equal Sign)", "duration": "114", "playcount": "19782249", "listeners": "282209", "url": "https://www.last.fm/music/j-hope/_/=+(Equal+Sign)", "streamable": {"#text": "0", "fulltrack": "0"}, "artist": {"name": "j-hope", "url": "https://www.last.fm/music/j-hope"}, "image": [{"#text": "https://lastfm.freetls.fastly.net/i/u/34s/2a96cbd8b46e442fc41c2b86b821562f.png", "size": "small"}, {"#text": "https://lastfm.freetls.fastly.net/i/u/64s/2a96cbd8b46e442fc41c2b86b821562f.png", "size": "medium"}, {"#text": "https://lastfm.freetls.fastly.net/i/u/174s/2a96cbd8b46e442fc41c2b86b821562f.png", "size": "large"}, {"#text": "https://lastfm.freetls.fastly.net/i/u/300x300/2a96cbd8b46e442fc41c2b86b821562f.png", "size": "extralarge"}]}, {"name": "You Know What", "duration": "271", "playcount": "1298022", "listeners": "170235", "mbid": "08162915-859b-4f6d-9a09-82ee6fefd32d", "url": "https://www.last.fm/music/N.E.R.D/_/You+Know+What", "streamable": {"#text": "0", "fulltrack": "0"}, "artist": {"name": "N.E.R.D", "mbid": "3fb49f5a-fdc0-4789-9c84-22b38b3f3cb5", "url": "https://www.last.fm/music/N.E.R.D"}, "image": [{"#text": "https://lastfm.freetls.fastly.net/i/u/34s/2a96cbd8b46e442fc41c2b86b821562f.png", "size": "small"}, {"#text": "https://lastfm.freetls.fastly.net/i/u/64s/2a96cbd8b46e442fc41c2b86b821562f.png", "size": "medium"}, {"#text": "https://lastfm.freetls.fastly.net/i/u/174s/2a96cbd8b46e442fc41c2b86b821562f.png", "size": "large"}, {"#text": "https://lastfm.freetls.fastly.net/i/u/300x300/2a96cbd8b46e442fc41c2b86b821562f.png", "size": "extralarge"}]}, {"name": "Downtown", "duration": "193", "playcount": "6260926", "listeners": "464242", "mbid": "17be188f-09da-4dd3-ae99-f48322049fd2", "url": "https://www.last.fm/music/Anitta/_/Downtown", "streamable": {"#text": "0", "fulltrack": "0"}, "artist": {"name": "Anitta", "mbid": "d606b860-cc03-4959-a3fd-3a24bccf2560", "url": "https://www.last.fm/music/Anitta"}, "image": [{"#text": "https://lastfm.freetls.fastly.net/i/u/34s/2a96cbd8b46e442fc41c2b86b821562f.png", "size": "small"}, {"#text": "https://lastfm.freetls.fastly.net/i/u/64s/2a96cbd8b46e442fc41c2b86b821562f.png", "size": "medium"}, {"#text": "https://lastfm.freetls.fastly.net/i/u/174s/2a96cbd8b46e442fc41c2b86b821562f.png", "size": "large"}, {"#text": "https://lastfm.freetls.fastly.net/i/u/300x300/2a96cbd8b46e442fc41c2b86b821562f.png", "size": "extralarge"}]}, {"name": "\u30c8\u30fc\u30ad\u30e7\u30fc\u30ec\u30ae\u30fc", "duration": "260", "playcount": "2133478", "listeners": "288041", "mbid": "2d0c6434-7f3f-419d-8f2d-3516fa420e71", "url": "https://www.last.fm/music/Masayoshi+Takanaka/_/%E3%83%88%E3%83%BC%E3%82%AD%E3%83%A7%E3%83%BC%E3%83%AC%E3%82%AE%E3%83%BC", "streamable": {"#text": "0", "fulltrack": "0"}, "artist": {"name": "Masayoshi Takanaka", "mbid": "facf743e-1231-410d-bdf1-9ba11a6a4f3c", "url": "https://www.last.fm/music/Masayoshi+Takanaka"}, "image": [{"#text": "https://lastfm.freetls.fastly.net/i/u/34s/2a96cbd8b46e442fc41c2b86b821562f.png", "size": "small"}, {"#text": "https://lastfm.freetls.fastly.net/i/u/64s/2a96cbd8b46e442fc41c2b86b821562f.png", "size": "medium"}, {"#text": "https://lastfm.freetls.fastly.net/i/u/174s/2a96cbd8b46e442fc41c2b86b821562f.png", "size": "large"}, {"#text": "https://lastfm.freetls.fastly.net/i/u/300x300/2a96cbd8b46e442fc41c2b86b821562f.png", "size": "extralarge"}]}, {"name": "Teardrops", "duration": "215", "playcount": "4583967", "listeners": "323950", "mbid": "1502ae17-181b-4711-8f2e-60325e877534", "url": "https://www.last.fm/music/Bring+Me+the+Horizon/_/Teardrops", "streamable": {"#text": "0", "fulltrack": "0"}, "artist": {"name": "Bring Me the Horizon", "mbid": "074e3847-f67f-49f9-81f1-8c8cea147e8e", "url": "https://www.last.fm/music/Bring+Me+the+Horizon"}, "image": [{"#text": "https://lastfm.freetls.fastly.net/i/u/34s/2a96cbd8b46e442fc41c2b86b821562f.png", "size": "small"}, {"#text": "https://lastfm.freetls.fastly.net/i/u/64s/2a96cbd8b46e442fc41c2b86b821562f.png", "size": "medium"}, {"#text": "https://lastfm.freetls.fastly.net/i/u/174s/2a96cbd8b46e442fc41c2b86b821562f.png", "size": "large"}, {"#text": "https://lastfm.freetls.fastly.net/i/u/300x300/2a96cbd8b46e442fc41c2b86b821562f.png", "size": "extralarge"}]}, {"name": "seoul (prod. HONNE)", "duration": "275", "playcount": "13758823", "listeners": "368859", "url": "https://www.last.fm/music/RM/_/seoul+(prod.+HONNE)", "streamable": {"#text": "0", "fulltrack": "0"}, "artist": {"name": "RM", "mbid": "0c33fb3f-50ab-4eba-adb4-7e4faa9bcc54", "url": "https://www.last.fm/music/RM"}, "image": [{"#text": "https://lastfm.freetls.fastly.net/i/u/34s/2a96cbd8b46e442fc41c2b86b821562f.png", "size": "small"}, {"#text": "https://lastfm.freetls.fastly.net/i/u/64s/2a96cbd8b46e442fc41c2b86b821562f.png", "size": "medium"}, {"#text": "https://lastfm.freetls.fastly.net/i/u/174s/2a96cbd8b46e442fc41c2b86b821562f.png", "size": "large"}, {"#text": "https://lastfm.freetls.fastly.net/i/u/300x300/2a96cbd8b46e442fc41c2b86b821562f.png", "size": "extralarge"}]}, {"name": "Smooth (feat. Rob Thomas)", "duration": "295", "playcount": "3805948", "listeners": "504149", "mbid": "4d14cc27-57a9-3196-9eb7-2bef0d2e066f", "url": "https://www.last.fm/music/Santana/_/Smooth+(feat.+Rob+Thomas)", "streamable": {"#text": "0", "fulltrack": "0"}, "artist": {"name": "Santana", "mbid": "9a3bf45c-347d-4630-894d-7cf3e8e0b632", "url": "https://www.last.fm/music/Santana"}, "image": [{"#text": "https://lastfm.freetls.fastly.net/i/u/34s/2a96cbd8b46e442fc41c2b86b821562f.png", "size": "small"}, {"#text": "https://lastfm.freetls.fastly.net/i/u/64s/2a96cbd8b46e442fc41c2b86b821562f.png", "size": "medium"}, {"#text": "https://lastfm.freetls.fastly.net/i/u/174s/2a96cbd8b46e442fc41c2b86b821562f.png", "size": "large"}, {"#text": "https://lastfm.freetls.fastly.net/i/u/300x300/2a96cbd8b46e442fc41c2b86b821562f.png", "size": "extralarge"}]}, {"name": "The Night Is Still Young", "duration": "162", "playcount": "5302796", "listeners": "592111", "mbid": "daa0f31f-2bc0-473b-a5ca-5c2d23041cf4", "url": "https://www.last.fm/music/Nicki+Minaj/_/The+Night+Is+Still+Young", "streamable": {"#text": "0", "fulltrack": "0"}, "artist": {"name": "Nicki Minaj", "mbid": "1036b808-f58c-4a3e-b461-a2c4492ecf1b", "url": "https://www.last.fm/music/Nicki+Minaj"}, "image": [{"#text": "https://lastfm.freetls.fastly.net/i/u/34s/2a96cbd8b46e442fc41c2b86b821562f.png", "size": "small"}, {"#text": "https://lastfm.freetls.fastly.net/i/u/64s/2a96cbd8b46e442fc41c2b86b821562f.png", "size": "medium"}, {"#text": "https://lastfm.freetls.fastly.net/i/u/174s/2a96cbd8b46e442fc41c2b86b821562f.png", "size": "large"}, {"#text": "https://lastfm.freetls.fastly.net/i/u/300x300/2a96cbd8b46e442fc41c2b86b821562f.png", "size": "extralarge"}]}, {"name": "BABY I'M BACK", "duration": "171", "playcount": "3147414", "listeners": "253102", "mbid": "7e05b9d5-2430-426f-87a4-13890db3eac6", "url": "https://www.last.fm/music/The+Kid+LAROI/_/BABY+I%27M+BACK", "streamable": {"#text": "0", "fulltrack": "0"}, "artist": {"name": "The Kid LAROI", "mbid": "80609a00-b394-4a49-975b-2db6b543fa97", "url": "https://www.last.fm/music/The+Kid+LAROI"}, "image": [{"#text": "https://lastfm.freetls.fastly.net/i/u/34s/2a96cbd8b46e442fc41c2b86b821562f.png", "size": "small"}, {"#text": "https://lastfm.freetls.fastly.net/i/u/64s/2a96cbd8b46e442fc41c2b86b821562f.png", "size": "medium"}, {"#text": "https://lastfm.freetls.fastly.net/i/u/174s/2a96cbd8b46e442fc41c2b86b821562f.png", "size": "large"}, {"#text": "https://lastfm.freetls.fastly.net/i/u/300x300/2a96cbd8b46e442fc41c2b86b821562f.png", "size": "extralarge"}]}, {"name": "Speed Trials", "duration": "195", "playcount": "6679368", "listeners": "644110", "mbid": "04270e1b-4fb2-461b-9d11-195229909cf7", "url": "https://www.last.fm/music/Elliott+Smith/_/Speed+Trials", "streamable": {"#text": "0", "fulltrack": "0"}, "artist": {"name": "Elliott Smith", "mbid": "03ad1736-b7c9-412a-b442-82536d63a5c4", "url": "https://www.last.fm/music/Elliott+Smith"}, "image": [{"#text": "https://lastfm.freetls.fastly.net/i/u/34s/2a96cbd8b46e442fc41c2b86b821562f.png", "size": "small"}, {"#text": "https://lastfm.freetls.fastly.net/i/u/64s/2a96cbd8b46e442fc41c2b86b821562f.png", "size": "medium"}, {"#text": "https://lastfm.freetls.fastly.net/i/u/174s/2a96cbd8b46e442fc41c2b86b821562f.png", "size": "large"}, {"#text": "https://lastfm.freetls.fastly.net/i/u/300x300/2a96cbd8b46e442fc41c2b86b821562f.png", "size": "extralarge"}]}, {"name": "OMG (feat. will.i.am)", "duration": "269", "playcount": "4233407", "listeners": "816405", "url": "https://www.last.fm/music/Usher/_/OMG+(feat.+will.i.am)", "streamable": {"#text": "0", "fulltrack": "0"}, "artist": {"name": "Usher", "mbid": "3414d446-735a-443c-931f-10634f57e5b9", "url": "https://www.last.fm/music/Usher"}, "image": [{"#text": "https://lastfm.freetls.fastly.net/i/u/34s/2a96cbd8b46e442fc41c2b86b821562f.png", "size": "small"}, {"#text": "https://lastfm.freetls.fastly.net/i/u/64s/2a96cbd8b46e442fc41c2b86b821562f.png", "size": "medium"}, {"#text": "https://lastfm.freetls.fastly.net/i/u/174s/2a96cbd8b46e442fc41c2b86b821562f.png", "size": "large"}, {"#text": "https://lastfm.freetls.fastly.net/i/u/300x300/2a96cbd8b46e442fc41c2b86b821562f.png", "size": "extralarge"}]}, {"name": "Vox Dei", "duration": "74", "playcount": "782461", "listeners": "45199", "url": "https://www.last.fm/music/HAZBIN+HOTEL/_/Vox+Dei", "streamable": {"#text": "0", "fulltrack": "0"}, "artist": {"name": "HAZBIN HOTEL", "url": "https://www.last.fm/music/HAZBIN+HOTEL"}, "image": [{"#text": "https://lastfm.freetls.fastly.net/i/u/34s/2a96cbd8b46e442fc41c2b86b821562f.png", "size": "small"}, {"#text": "https://lastfm.freetls.fastly.net/i/u/64s/2a96cbd8b46e442fc41c2b86b821562f.png", "size": "medium"}, {"#text": "https://lastfm.freetls.fastly.net/i/u/174s/2a96cbd8b46e442fc41c2b86b821562f.png", "size": "large"}, {"#text": "https://lastfm.freetls.fastly.net/i/u/300x300/2a96cbd8b46e442fc41c2b86b821562f.png", "size": "extralarge"}]}, {"name": "I Luv U", "duration": "0", "playcount": "64893", "listeners": "32549", "url": "https://www.last.fm/music/Fred+again../_/I+Luv+U", "streamable": {"#text": "0", "fulltrack": "0"}, "artist": {"name": "Fred again..", "url": "https://www.last.fm/music/Fred+again.."}, "image": [{"#text": "https://lastfm.freetls.fastly.net/i/u/34s/2a96cbd8b46e442fc41c2b86b821562f.png", "size": "small"}, {"#text": "https://lastfm.freetls.fastly.net/i/u/64s/2a96cbd8b46e442fc41c2b86b821562f.png", "size": "medium"}, {"#text": "https://lastfm.freetls.fastly.net/i/u/174s/2a96cbd8b46e442fc41c2b86b821562f.png", "size": "large"}, {"#text": "https://lastfm.freetls.fastly.net/i/u/300x300/2a96cbd8b46e442fc41c2b86b821562f.png", "size": "extralarge"}]}, {"name": "Creep - Acoustic", "duration": "0", "playcount": "2779453", "listeners": "361779", "mbid": "28467436-c39b-424b-be16-edac70df8dc3", "url": "https://www.last.fm/music/Radiohead/_/Creep+-+Acoustic", "streamable": {"#text": "0", "fulltrack": "0"}, "artist": {"name": "Radiohead", "mbid": "a74b1b7f-71a5-4011-9441-d0b5e4122711", "url": "https://www.last.fm/music/Radiohead"}, "image": [{"#text": "https://lastfm.freetls.fastly.net/i/u/34s/2a96cbd8b46e442fc41c2b86b821562f.png", "size": "small"}, {"#text": "https://lastfm.freetls.fastly.net/i/u/64s/2a96cbd8b46e442fc41c2b86b821562f.png", "size": "medium"}, {"#text": "https://lastfm.freetls.fastly.net/i/u/174s/2a96cbd8b46e442fc41c2b86b821562f.png", "size": "large"}, {"#text": "https://lastfm.freetls.fastly.net/i/u/300x300/2a96cbd8b46e442fc41c2b86b821562f.png", "size": "extralarge"}]}, {"name": "2 + 2 = 5", "duration": "199", "playcount": "6531911", "listeners": "724763", "mbid": "14692e9b-8a4f-40ce-b2a4-5ce1a45599bb", "url": "https://www.last.fm/music/Radiohead/_/2+%252B+2+=+5", "streamable": {"#text": "0", "fulltrack": "0"}, "artist": {"name": "Radiohead", "mbid": "a74b1b7f-71a5-4011-9441-d0b5e4122711", "url": "https://www.last.fm/music/Radiohead"}, "image": [{"#text": "https://lastfm.freetls.fastly.net/i/u/34s/2a96cbd8b46e442fc41c2b86b821562f.png", "size": "small"}, {"#text": "https://lastfm.freetls.fastly.net/i/u/64s/2a96cbd8b46e442fc41c2b86b821562f.png", "size": "medium"}, {"#text": "https://lastfm.freetls.fastly.net/i/u/174s/2a96cbd8b46e442fc41c2b86b821562f.png", "size": "large"}, {"#text": "https://lastfm.freetls.fastly.net/i/u/300x300/2a96cbd8b46e442fc41c2b86b821562f.png", "size": "extralarge"}]}, {"name": "Skinny Love", "duration": "344", "playcount": "22998490", "listeners": "1735905", "mbid": "3f77de2e-d506-3c5c-bf9d-5b019313b9a6", "url": "https://www.last.fm/music/Bon+Iver/_/Skinny+Love", "streamable": {"#text": "0", "fulltrack": "0"}, "artist": {"name": "Bon Iver", "mbid": "437a0e49-c6ae-42f6-a6c1-84f25ed366bc", "url": "https://www.last.fm/music/Bon+Iver"}, "image": [{"#text": "https://lastfm.freetls.fastly.net/i/u/34s/2a96cbd8b46e442fc41c2b86b821562f.png", "size": "small"}, {"#text": "https://lastfm.freetls.fastly.net/i/u/64s/2a96cbd8b46e442fc41c2b86b821562f.png", "size": "medium"}, {"#text": "https://lastfm.freetls.fastly.net/i/u/174s/2a96cbd8b46e442fc41c2b86b821562f.png", "size": "large"}, {"#text": "https://lastfm.freetls.fastly.net/i/u/300x300/2a96cbd8b46e442fc41c2b86b821562f.png", "size": "extralarge"}]}, {"name": "O Come All Ye Faithful - Spotify Singles Holiday", "duration": "185", "playcount": "68993", "listeners": "45243", "mbid": "0c4e0c38-74a9-4c7e-9f41-21b794ac8b18", "url": "https://www.last.fm/music/Jordan+Davis/_/O+Come+All+Ye+Faithful+-+Spotify+Singles+Holiday", "streamable": {"#text": "0", "fulltrack": "0"}, "artist": {"name": "Jordan Davis", "mbid": "e90eaba7-aa99-40f6-8348-8b822dcf20d7", "url": "https://www.last.fm/music/Jordan+Davis"}, "image": [{"#text": "https://lastfm.freetls.fastly.net/i/u/34s/2a96cbd8b46e442fc41c2b86b821562f.png", "size": "small"}, {"#text": "https://lastfm.freetls.fastly.net/i/u/64s/2a96cbd8b46e442fc41c2b86b821562f.png", "size": "medium"}, {"#text": "https://lastfm.freetls.fastly.net/i/u/174s/2a96cbd8b46e442fc41c2b86b821562f.png", "size": "large"}, {"#text": "https://lastfm.freetls.fastly.net/i/u/300x300/2a96cbd8b46e442fc41c2b86b821562f.png", "size": "extralarge"}]}], "@attr": {"page": "90", "perPage": "50", "totalPages": "18978371", "total": "948918503"}}}