{"tracks": {"track": [{"name": "On Top of the World", "duration": "192", "playcount": "9486731", "listeners": "1147108", "url": "https://www.last.fm/music/Imagine+Dragons/_/On+Top+of+the+World", "streamable": {"#text": "0", "fulltrack": "0"}, "artist": {"name": "Imagine Dragons", "mbid": "012151a8-0f9a-44c9-997f-ebd68b5389f9", "url": "https://www.last.fm/music/Imagine+Dragons"}, "image": [{"#text": "https://lastfm.freetls.fastly.net/i/u/34s/2a96cbd8b46e442fc41c2b86b821562f.png", "size": "small"}, {"#text": "https://lastfm.freetls.fastly.net/i/u/64s/2a96cbd8b46e442fc41c2b86b821562f.png", "size": "medium"}, {"#text": "https://lastfm.freetls.fastly.net/i/u/174s/2a96cbd8b46e442fc41c2b86b821562f.png", "size": "large"}, {"#text": "https://lastfm.freetls.fastly.net/i/u/300x300/2a96cbd8b46e442fc41c2b86b821562f.png", "size": "extralarge"}]}, {"name": "BOOGIE", "duration": "193", "playcount": "5848321", "listeners": "494230", "mbid": "07b8c6f7-7060-4c96-b153-3c074484a7ac", "url": "https://www.last.fm/music/BROCKHAMPTON/_/BOOGIE", "streamable": {"#text": "0", "fulltrack": "0"}, "artist": {"name": "BROCKHAMPTON", "mbid": "3ac96b4c-4f42-48c8-b793-84dbf54d7ac6", "url": "https://www.last.fm/music/BROCKHAMPTON"}, "image": [{"#text": "https://lastfm.freetls.fastly.net/i/u/34s/2a96cbd8b46e442fc41c2b86b821562f.png", "size": "small"}, {"#text": "https://lastfm.freetls.fastly.net/i/u/64s/2a96cbd8b46e442fc41c2b86b821562f.png", "size": "medium"}, {"#text": "https://lastfm.freetls.fastly.net/i/u/174s/2a96cbd8b46e442fc41c2b86b821562f.png", "size": "large"}, {"#text": "https://lastfm.freetls.fastly.net/i/u/300x300/2a96cbd8b46e442fc41c2b86b821562f.png", "size": "extralarge"}]}, {"name": "Frequency", "duration": "163", "playcount": "646426", "listeners": "80928", "mbid": "4ebb887c-fe07-4098-84a1-5e47be10330c", "url": "https://www.last.fm/music/Demi+Lovato/_/Frequency", "streamable": {"#text": "0", "fulltrack": "0"}, "artist": {"name": "Demi Lovato", "mbid": "faf4cefb-036c-4c88-b93a-5b03dd0a0e6b", "url": "https://www.last.fm/music/Demi+Lovato"}, "image": [{"#text": "https://lastfm.freetls.fastly.net/i/u/34s/2a96cbd8b46e442fc41c2b86b821562f.png", "size": "small"}, {"#text": "https://lastfm.freetls.fastly.net/i/u/64s/2a96cbd8b46e442fc41c2b86b821562f.png", "size": "medium"}, {"#text": "https://lastfm.freetls.fastly.net/i/u/174s/2a96cbd8b46e442fc41c2b86b821562f.png", "size": "large"}, {"#text": "https://lastfm.freetls.fastly.net/i/u/300x300/2a96cbd8b46e442fc41c2b86b821562f.png", "size": "extralarge"}]}, {"name": "Too Close", "duration": "170", "playcount": "4474655", "listeners": "460853", "mbid": "8cc95c31-2241-4209-8647-e31030e7f727", "url": "https://www.last.fm/music/Sir+Chloe/_/Too+Close", "streamable": {"#text": "0", "fulltrack": "0"}, "artist": {"name": "Sir Chloe", "mbid": "3c3a1ea4-922a-4a90-b1aa-b7763d6dbf20", "url": "https://www.last.fm/music/Sir+Chloe"}, "image": [{"#text": "https://lastfm.freetls.fastly.net/i/u/34s/2a96cbd8b46e442fc41c2b86b821562f.png", "size": "small"}, {"#text": "https://lastfm.freetls.fastly.net/i/u/64s/2a96cbd8b46e442fc41c2b86b821562f.png", "size": "medium"}, {"#text": "https://lastfm.freetls.fastly.net/i/u/174s/2a96cbd8b46e442fc41c2b86b821562f.png", "size": "large"}, {"#text": "https://lastfm.freetls.fastly.net/i/u/300x300/2a96cbd8b46e442fc41c2b86b821562f.png", "size": "extralarge"}]}, {"name": "Lose It", "duration": "140", "playcount": "4447490", "listeners": "248726", "mbid": "e79c3378-9aaf-4a1b-84c9-89f9b90ca6d3", "url": "https://www.last.fm/music/Ken+Carson/_/Lose+It", "streamable": {"#text": "0", "fulltrack": "0"}, "artist": {"name": "Ken Carson", "mbid": "84d4283e-903a-42c4-a0d2-d3949bfa1f3f", "url": "https://www.last.fm/music/Ken+Carson"}, "image": [{"#text": "https://lastfm.freetls.fastly.net/i/u/34s/2a96cbd8b46e442fc41c2b86b821562f.png", "size": "small"}, {"#text": "https://lastfm.freetls.fastly.net/i/u/64s/2a96cbd8b46e442fc41c2b86b821562f.png", "size": "medium"}, {"#text": "https://lastfm.freetls.fastly.net/i/u/174s/2a96cbd8b46e442fc41c2b86b821562f.png", "size": "large"}, {"#text": "https://lastfm.freetls.fastly.net/i/u/300x300/2a96cbd8b46e442fc41c2b86b821562f.png", "size": "extralarge"}]}, {"name": "Foi assim", "duration": "0", "playcount": "237188", "listeners": "41326", "url": "https://www.last.fm/music/Sotam/_/Foi+assim", "streamable": {"#text": "0", "fulltrack": "0"}, "artist": {"name": "Sotam", "url": "https://www.last.fm/music/Sotam"}, "image": [{"#text": "https://lastfm.freetls.fastly.net/i/u/34s/2a96cbd8b46e442fc41c2b86b821562f.png", "size": "small"}, {"#text": "https://lastfm.freetls.fastly.net/i/u/64s/2a96cbd8b46e442fc41c2b86b821562f.png", "size": "medium"}, {"#text": "https://lastfm.freetls.fastly.net/i/u/174s/2a96cbd8b46e442fc41c2b86b821562f.png", "size": "large"}, {"#text": "https://lastfm.freetls.fastly.net/i/u/300x300/2a96cbd8b46e442fc41c2b86b821562f.png", "size": "extralarge"}]}, {"name": "No Comma", "duration": "161", "playcount": "1219479", "listeners": "103874", "url": "https://www.last.fm/music/Slayyyter/_/No+Comma", "streamable": {"#text": "0", "fulltrack": "0"}, "artist": {"name": "Slayyyter", "mbid": "9058d01e-8afc-47a4-8664-621fb5f159c0", "url": "https://www.last.fm/music/Slayyyter"}, "image": [{"#text": "https://lastfm.freetls.fastly.net/i/u/34s/2a96cbd8b46e442fc41c2b86b821562f.png", "size": "small"}, {"#text": "https://lastfm.freetls.fastly.net/i/u/64s/2a96cbd8b46e442fc41c2b86b821562f.png", "size": "medium"}, {"#text": "https://lastfm.freetls.fastly.net/i/u/174s/2a96cbd8b46e442fc41c2b86b821562f.png", "size": "large"}, {"#text": "https://lastfm.freetls.fastly.net/i/u/300x300/2a96cbd8b46e442fc41c2b86b821562f.png", "size": "extralarge"}]}, {"name": "Crazy Story", "duration": "146", "playcount": "3091065", "listeners": "277238", "mbid": "0f3f3844-372c-47c2-b840-0ac0048d869a", "url": "https://www.last.fm/music/King+Von/_/Crazy+Story", "streamable": {"#text": "0", "fulltrack": "0"}, "artist": {"name": "King Von", "mbid": "a542a08c-9434-4028-8da5-3120c4fdd3fb", "url": "https://www.last.fm/music/King+Von"}, "image": [{"#text": "https://lastfm.freetls.fastly.net/i/u/34s/2a96cbd8b46e442fc41c2b86b821562f.png", "size": "small"}, {"#text": "https://lastfm.freetls.fastly.net/i/u/64s/2a96cbd8b46e442fc41c2b86b821562f.png", "size": "medium"}, {"#text": "https://lastfm.freetls.fastly.net/i/u/174s/2a96cbd8b46e442fc41c2b86b821562f.png", "size": "large"}, {"#text": "https://lastfm.freetls.fastly.net/i/u/300x300/2a96cbd8b46e442fc41c2b86b821562f.png", "size": "extralarge"}]}, {"name": "Accordion", "duration": "116", "playcount": "8971919", "listeners": "817506", "mbid": "1e499cce-b037-353d-b997-f2b6c30beeb2", "url": "https://www.last.fm/music/Madvillain/_/Accordion", "streamable": {"#text": "0", "fulltrack": "0"}, "artist": {"name": "Madvillain", "mbid": "4e024037-14b7-4aea-99ad-c6ace63b9620", "url": "https://www.last.fm/music/Madvillain"}, "image": [{"#text": "https://lastfm.freetls.fastly.net/i/u/34s/2a96cbd8b46e442fc41c2b86b821562f.png", "size": "small"}, {"#text": "https://lastfm.freetls.fastly.net/i/u/64s/2a96cbd8b46e442fc41c2b86b821562f.png", "size": "medium"}, {"#text": "https://lastfm.freetls.fastly.net/i/u/174s/2a96cbd8b46e442fc41c2b86b821562f.png", "size": "large"}, {"#text": "https://lastfm.freetls.fastly.net/i/u/300x300/2a96cbd8b46e442fc41c2b86b821562f.png", "size": "extralarge"}]}, {"name": "SI NO ES CONTIGO - REMIX", "duration": "0", "playcount": "2259767", "listeners": "166057", "url": "https://www.last.fm/music/Cris+Mj/_/SI+NO+ES+CONTIGO+-+REMIX", "streamable": {"#text": "0", "fulltrack": "0"}, "artist": {"name": "Cris Mj", "url": "https://www.last.fm/music/Cris+Mj"}, "image": [{"#text": "https://lastfm.freetls.fastly.net/i/u/34s/2a96cbd8b46e442fc41c2b86b821562f.png", "size": "small"}, {"#text": "https://lastfm.freetls.fastly.net/i/u/64s/2a96cbd8b46e442fc41c2b86b821562f.png", "size": "medium"}, {"#text": "https://lastfm.freetls.fastly.net/i/u/174s/2a96cbd8b46e442fc41c2b86b821562f.png", "size": "large"}, {"#text": "https://lastfm.freetls.fastly.net/i/u/300x300/2a96cbd8b46e442fc41c2b86b821562f.png", "size": "extralarge"}]}, {"name": "In My Head", "duration": "354", "playcount": "5272924", "listeners": "507098", "mbid": "81b3c6f8-8c1d-4a42-8e99-9bcc1faccce8", "url": "https://www.last.fm/music/Bedroom/_/In+My+Head", "streamable": {"#text": "0", "fulltrack": "0"}, "artist": {"name": "Bedroom", "mbid": "3f23ba50-315c-4582-bfbf-f15421309d9b", "url": "https://www.last.fm/music/Bedroom"}, "image": [{"#text": "https://lastfm.freetls.fastly.net/i/u/34s/2a96cbd8b46e442fc41c2b86b821562f.png", "size": "small"}, {"#text": "https://lastfm.freetls.fastly.net/i/u/64s/2a96cbd8b46e442fc41c2b86b821562f.png", "size": "medium"}, {"#text": "https://lastfm.freetls.fastly.net/i/u/174s/2a96cbd8b46e442fc41c2b86b821562f.png", "size": "large"}, {"#text": "https://lastfm.freetls.fastly.net/i/u/300x300/2a96cbd8b46e442fc41c2b86b821562f.png", "size": "extralarge"}]}, {"name": "Afraid To Feel", "duration": "177", "playcount": "3866444", "listeners": "448645", "mbid": "d71f7d62-f7fc-4907-ba37-3f97a12448f7", "url": "https://www.last.fm/music/LF+System/_/Afraid+To+Feel", "streamable": {"#text": "0", "fulltrack": "0"}, "artist": {"name": "LF System", "url": "https://www.last.fm/music/LF+System"}, "image": [{"#text": "https://lastfm.freetls.fastly.net/i/u/34s/2a96cbd8b46e442fc41c2b86b821562f.png", "size": "small"}, {"#text": "https://lastfm.freetls.fastly.net/i/u/64s/2a96cbd8b46e442fc41c2b86b821562f.png", "size": "medium"}, {"#text": "https://lastfm.freetls.fastly.net/i/u/174s/2a96cbd8b46e442fc41c2b86b821562f.png", "size": "large"}, {"#text": "https://lastfm.freetls.fastly.net/i/u/300x300/2a96cbd8b46e442fc41c2b86b821562f.png", "size": "extralarge"}]}, {"name": "Um Girassol da Cor do Seu Cabelo", "duration": "252", "playcount": "2400410", "listeners": "225154", "mbid": "3344825d-ad05-3bc5-b4b8-a63b1257092c", "url": "https://www.last.fm/music/L%C3%B4+Borges/_/Um+Girassol+da+Cor+do+Seu+Cabelo", "streamable": {"#text": "0", "fulltrack": "0"}, "artist": {"name": "L\u00f4 Borges", "mbid": "5bddb0fa-66f7-47c8-bf00-afecab627d59", "url": "https://www.last.fm/music/L%C3%B4+Borges"}, "image": [{"#text": "https://lastfm.freetls.fastly.net/i/u/34s/2a96cbd8b46e442fc41c2b86b821562f.png", "size": "small"}, {"#text": "https://lastfm.freetls.fastly.net/i/u/64s/2a96cbd8b46e442fc41c2b86b821562f.png", "size": "medium"}, {"#text": "https://lastfm.freetls.fastly.net/i/u/174s/2a96cbd8b46e442fc41c2b86b821562f.png", "size": "large"}, {"#text": "https://lastfm.freetls.fastly.net/i/u/300x300/2a96cbd8b46e442fc41c2b86b821562f.png", "size": "extralarge"}]}, {"name": "Savior", "duration": "224", "playcount": "7031311", "listeners": "606460", "url": "https://www.last.fm/music/Kendrick+Lamar/_/Savior", "streamable": {"#text": "0", "fulltrack": "0"}, "artist": {"name": "Kendrick Lamar", "mbid": "381086ea-f511-4aba-bdf9-71c753dc5077", "url": "https://www.last.fm/music/Kendrick+Lamar"}, "image": [{"#text": "https://lastfm.freetls.fastly.net/i/u/34s/2a96cbd8b46e442fc41c2b86b821562f.png", "size": "small"}, {"#text": "https://lastfm.freetls.fastly.net/i/u/64s/2a96cbd8b46e442fc41c2b86b821562f.png", "size": "medium"}, {"#text": "https://lastfm.freetls.fastly.net/i/u/174s/2a96cbd8b46e442fc41c2b86b821562f.png", "size": "large"}, {"#text": "https://lastfm.freetls.fastly.net/i/u/300x300/2a96cbd8b46e442fc41c2b86b821562f.png", "size": "extralarge"}]}, {"name": "SKITZO (feat. Young Thug)", "duration": "366", "playcount": "4627278", "listeners": "389623", "mbid": "e356a034-f31d-436d-a6f5-fb0a15249add", "url": "https://www.last.fm/music/Travis+Scott/_/SKITZO+(feat.+Young+Thug)", "streamable": {"#text": "0", "fulltrack": "0"}, "artist": {"name": "Travis Scott", "mbid": "e4a51f17-a57b-47b1-b37b-f552d0f8e9e6", "url": "https://www.last.fm/music/Travis+Scott"}, "image": [{"#text": "https://lastfm.freetls.fastly.net/i/u/34s/2a96cbd8b46e442fc41c2b86b821562f.png", "size": "small"}, {"#text": "https://lastfm.freetls.fastly.net/i/u/64s/2a96cbd8b46e442fc41c2b86b821562f.png", "size": "medium"}, {"#text": "https://lastfm.freetls.fastly.net/i/u/174s/2a96cbd8b46e442fc41c2b86b821562f.png", "size": "large"}, {"#text": "https://lastfm.freetls.fastly.net/i/u/300x300/2a96cbd8b46e442fc41c2b86b821562f.png", "size": "extralarge"}]}, {"name": "Down With Me", "duration": "120", "playcount": "3894011", "listeners": "319907", "mbid": "7b5023d9-3fc3-4e30-9550-825e00b6c60c", "url": "https://www.last.fm/music/Lil+Tecca/_/Down+With+Me", "streamable": {"#text": "0", "fulltrack": "0"}, "artist": {"name": "Lil Tecca", "mbid": "e6fdf3f9-8077-4126-b0cf-94da9a8b627e", "url": "https://www.last.fm/music/Lil+Tecca"}, "image": [{"#text": "https://lastfm.freetls.fastly.net/i/u/34s/2a96cbd8b46e442fc41c2b86b821562f.png", "size": "small"}, {"#text": "https://lastfm.freetls.fastly.net/i/u/64s/2a96cbd8b46e442fc41c2b86b821562f.png", "size": "medium"}, {"#text": "https://lastfm.freetls.fastly.net/i/u/174s/2a96cbd8b46e442fc41c2b86b821562f.png", "size": "large"}, {"#text": "https://lastfm.freetls.fastly.net/i/u/300x300/2a96cbd8b46e442fc41c2b86b821562f.png", "size": "extralarge"}]}, {"name": "Undisclosed Desires", "duration": "236", "playcount": "12434427", "listeners": "1064064", "mbid": "0029d6b6-07d1-48df-af6b-a12e361cd611", "url": "https://www.last.fm/music/Muse/_/Undisclosed+Desires", "streamable": {"#text": "0", "fulltrack": "0"}, "artist": {"name": "Muse", "mbid": "9c9f1380-2516-4fc9-a3e6-f9f61941d090", "url": "https://www.last.fm/music/Muse"}, "image": [{"#text": "https://lastfm.freetls.fastly.net/i/u/34s/2a96cbd8b46e442fc41c2b86b821562f.png", "size": "small"}, {"#text": "https://lastfm.freetls.fastly.net/i/u/64s/2a96cbd8b46e442fc41c2b86b821562f.png", "size": "medium"}, {"#text": "https://lastfm.freetls.fastly.net/i/u/174s/2a96cbd8b46e442fc41c2b86b821562f.png", "size": "large"}, {"#text": "https://lastfm.freetls.fastly.net/i/u/300x300/2a96cbd8b46e442fc41c2b86b821562f.png", "size": "extralarge"}]}, {"name": "instagram", "duration": "255", "playcount": "5167042", "listeners": "368878", "mbid": "4d72d095-205d-43d5-8ef0-8a4441d40741", "url": "https://www.last.fm/music/Dean/_/instagram", "streamable": {"#text": "0", "fulltrack": "0"}, "artist": {"name": "Dean", "mbid": "5fc2511f-a008-45c5-84b0-571c3e2e76e7", "url": "https://www.last.fm/music/Dean"}, "image": [{"#text": "https://lastfm.freetls.fastly.net/i/u/34s/2a96cbd8b46e442fc41c2b86b821562f.png", "size": "small"}, {"#text": "https://lastfm.freetls.fastly.net/i/u/64s/2a96cbd8b46e442fc41c2b86b821562f.png", "size": "medium"}, {"#text": "https://lastfm.freetls.fastly.net/i/u/174s/2a96cbd8b46e442fc41c2b86b821562f.png", "size": "large"}, {"#text": "https://lastfm.freetls.fastly.net/i/u/300x300/2a96cbd8b46e442fc41c2b86b821562f.png", "size": "extralarge"}]}, {"name": "Club Bizarre", "duration": "300", "playcount": "1189268", "listeners": "178547", "mbid": "01838d3a-df13-3448-a329-bf49bb12d3fc", "url": "https://www.last.fm/music/U96/_/Club+Bizarre", "streamable": {"#text": "0", "fulltrack": "0"}, "artist": {"name": "U96", "mbid": "5a2e73e9-15b3-4bd5-bd4b-7a331ead808a", "url": "https://www.last.fm/music/U96"}, "image": [{"#text": "https://lastfm.freetls.fastly.net/i/u/34s/2a96cbd8b46e442fc41c2b86b821562f.png", "size": "small"}, {"#text": "https://lastfm.freetls.fastly.net/i/u/64s/2a96cbd8b46e442fc41c2b86b821562f.png", "size": "medium"}, {"#text": "https://lastfm.freetls.fastly.net/i/u/174s/2a96cbd8b46e442fc41c2b86b821562f.png", "size": "large"}, {"#text": "https://lastfm.freetls.fastly.net/i/u/300x300/2a96cbd8b46e442fc41c2b86b821562f.png", "size": "extralarge"}]}, {"name": "Planet", "duration": "241", "playcount": "287440", "listeners": "67056", "mbid": "5a4ca257-49d2-46da-9626-141418dae9fa", "url": "https://www.last.fm/music/The+Neighbourhood/_/Planet", "streamable": {"#text": "0", "fulltrack": "0"}, "artist": {"name": "The Neighbourhood", "mbid": "53b06622-ec51-4924-a554-58b0affde6b5", "url": "https://www.last.fm/music/The+Neighbourhood"}, "image": [{"#text": "https://lastfm.freetls.fastly.net/i/u/34s/2a96cbd8b46e442fc41c2b86b821562f.png", "size": "small"}, {"#text": "https://lastfm.freetls.fastly.net/i/u/64s/2a96cbd8b46e442fc41c2b86b821562f.png", "size": "medium"}, {"#text": "https://lastfm.freetls.fastly.net/i/u/174s/2a96cbd8b46e442fc41c2b86b821562f.png", "size": "large"}, {"#text": "https://lastfm.freetls.fastly.net/i/u/300x300/2a96cbd8b46e442fc41c2b86b821562f.png", "size": "extralarge"}]}, {"name": "Wound Up Here (By Holdin On)", "duration": "208", "playcount": "432704", "listeners": "73666", "mbid": "624b9000-ed50-44c5-9a06-1651aa7aab1d", "url": "https://www.last.fm/music/Wednesday/_/Wound+Up+Here+(By+Holdin+On)", "streamable": {"#text": "0", "fulltrack": "0"}, "artist": {"name": "Wednesday", "mbid": "9af01d07-8f6e-4651-bdcb-38efae021af7", "url": "https://www.last.fm/music/Wednesday"}, "image": [{"#text": "https://lastfm.freetls.fastly.net/i/u/34s/2a96cbd8b46e442fc41c2b86b821562f.png", "size": "small"}, {"#text": "https://lastfm.freetls.fastly.net/i/u/64s/2a96cbd8b46e442fc41c2b86b821562f.png", "size": "medium"}, {"#text": "https://lastfm.freetls.fastly.net/i/u/174s/2a96cbd8b46e442fc41c2b86b821562f.png", "size": "large"}, {"#text": "https://lastfm.freetls.fastly.net/i/u/300x300/2a96cbd8b46e442fc41c2b86b821562f.png", "size": "extralarge"}]}, {"name": "Thinking About You", "duration": "396", "playcount": "2113544", "listeners": "278915", "mbid": "e6613a11-58b4-44ba-941c-6a0e9e8f6e1f", "url": "https://www.last.fm/music/Faye+Webster/_/Thinking+About+You", "streamable": {"#text": "0", "fulltrack": "0"}, "artist": {"name": "Faye Webster", "mbid": "ce4a1c08-6912-423f-bf6c-97ce69f5e89f", "url": "https://www.last.fm/music/Faye+Webster"}, "image": [{"#text": "https://lastfm.freetls.fastly.net/i/u/34s/2a96cbd8b46e442fc41c2b86b821562f.png", "size": "small"}, {"#text": "https://lastfm.freetls.fastly.net/i/u/64s/2a96cbd8b46e442fc41c2b86b821562f.png", "size": "medium"}, {"#text": "https://lastfm.freetls.fastly.net/i/u/174s/2a96cbd8b46e442fc41c2b86b821562f.png", "size": "large"}, {"#text": "https://lastfm.freetls.fastly.net/i/u/300x300/2a96cbd8b46e442fc41c2b86b821562f.png", "size": "extralarge"}]}, {"name": "Oh My Angel", "duration": "142", "playcount": "868574", "listeners": "166836", "mbid": "0cebd83b-f7fb-4efe-a277-be015ea97b6c", "url": "https://www.last.fm/music/Bertha+Tillman/_/Oh+My+Angel", "streamable": {"#text": "0", "fulltrack": "0"}, "artist": {"name": "Bertha Tillman", "mbid": "9d06d99d-4a54-4339-9365-310b842ca1a7", "url": "https://www.last.fm/music/Bertha+Tillman"}, "image": [{"#text": "https://lastfm.freetls.fastly.net/i/u/34s/2a96cbd8b46e442fc41c2b86b821562f.png", "size": "small"}, {"#text": "https://lastfm.freetls.fastly.net/i/u/64s/2a96cbd8b46e442fc41c2b86b821562f.png", "size": "medium"}, {"#text": "https://lastfm.freetls.fastly.net/i/u/174s/2a96cbd8b46e442fc41c2b86b821562f.png", "size": "large"}, {"#text": "https://lastfm.freetls.fastly.net/i/u/300x300/2a96cbd8b46e442fc41c2b86b821562f.png", "size": "extralarge"}]}, {"name": "Real Friends", "duration": "251", "playcount": "6700258", "listeners": "624502", "mbid": "157a7648-b84b-4093-b7d8-1003fbbb6482", "url": "https://www.last.fm/music/Kanye+West/_/Real+Friends", "streamable": {"#text": "0", "fulltrack": "0"}, "artist": {"name": "Kanye West", "url": "https://www.last.fm/music/Kanye+West"}, "image": [{"#text": "https://lastfm.freetls.fastly.net/i/u/34s/2a96cbd8b46e442fc41c2b86b821562f.png", "size": "small"}, {"#text": "https://lastfm.freetls.fastly.net/i/u/64s/2a96cbd8b46e442fc41c2b86b821562f.png", "size": "medium"}, {"#text": "https://lastfm.freetls.fastly.net/i/u/174s/2a96cbd8b46e442fc41c2b86b821562f.png", "size": "large"}, {"#text": "https://lastfm.freetls.fastly.net/i/u/300x300/2a96cbd8b46e442fc41c2b86b821562f.png", "size": "extralarge"}]}, {"name": "Daydream", "duration": "120", "playcount": "3601932", "listeners": "107788", "url": "https://www.last.fm/music/ENHYPEN/_/Daydream", "streamable": {"#text": "0", "fulltrack": "0"}, "artist": {"name": "ENHYPEN", "mbid": "95663592-1447-4579-90f7-c94733476667", "url": "https://www.last.fm/music/ENHYPEN"}, "image": [{"#text": "https://lastfm.freetls.fastly.net/i/u/34s/2a96cbd8b46e442fc41c2b86b821562f.png", "size": "small"}, {"#text": "https://lastfm.freetls.fastly.net/i/u/64s/2a96cbd8b46e442fc41c2b86b821562f.png", "size": "medium"}, {"#text": "https://lastfm.freetls.fastly.net/i/u/174s/2a96cbd8b46e442fc41c2b86b821562f.png", "size": "large"}, {"#text": "https://lastfm.freetls.fastly.net/i/u/300x300/2a96cbd8b46e442fc41c2b86b821562f.png", "size": "extralarge"}]}, {"name": "Cleopatra", "duration": "225", "playcount": "5091521", "listeners": "482088", "mbid": "147c079c-dd19-4550-808c-6ef44edc1f76", "url": "https://www.last.fm/music/The+Lumineers/_/Cleopatra", "streamable": {"#text": "0", "fulltrack": "0"}, "artist": {"name": "The Lumineers", "mbid": "bfcb6630-9b31-4e63-b11f-7b0363be72b5", "url": "https://www.last.fm/music/The+Lumineers"}, "image": [{"#text": "https://lastfm.freetls.fastly.net/i/u/34s/2a96cbd8b46e442fc41c2b86b821562f.png", "size": "small"}, {"#text": "https://lastfm.freetls.fastly.net/i/u/64s/2a96cbd8b46e442fc41c2b86b821562f.png", "size": "medium"}, {"#text": "https://lastfm.freetls.fastly.net/i/u/174s/2a96cbd8b46e442fc41c2b86b821562f.png", "size": "large"}, {"#text": "https://lastfm.freetls.fastly.net/i/u/300x300/2a96cbd8b46e442fc41c2b86b821562f.png", "size": "extralarge"}]}, {"name": "grave", "duration": "193", "playcount": "2306144", "listeners": "166907", "mbid": "1e4cf6fc-ea60-423d-88f7-5065f50f7981", "url": "https://www.last.fm/music/Tate+McRae/_/grave", "streamable": {"#text": "0", "fulltrack": "0"}, "artist": {"name": "Tate McRae", "mbid": "f9133869-f87c-459c-9aa7-2f176cda7e06", "url": "https://www.last.fm/music/Tate+McRae"}, "image": [{"#text": "https://lastfm.freetls.fastly.net/i/u/34s/2a96cbd8b46e442fc41c2b86b821562f.png", "size": "small"}, {"#text": "https://lastfm.freetls.fastly.net/i/u/64s/2a96cbd8b46e442fc41c2b86b821562f.png", "size": "medium"}, {"#text": "https://lastfm.freetls.fastly.net/i/u/174s/2a96cbd8b46e442fc41c2b86b821562f.png", "size": "large"}, {"#text": "https://lastfm.freetls.fastly.net/i/u/300x300/2a96cbd8b46e442fc41c2b86b821562f.png", "size": "extralarge"}]}, {"name": "Ends of the Earth", "duration": "286", "playcount": "3170239", "listeners": "439504", "mbid": "acb635b4-dc1a-45d1-9afd-903b8b375be3", "url": "https://www.last.fm/music/Lord+Huron/_/Ends+of+the+Earth", "streamable": {"#text": "0", "fulltrack": "0"}, "artist": {"name": "Lord Huron", "mbid": "51c76d97-0635-433c-b26d-66beb81657f8", "url": "https://www.last.fm/music/Lord+Huron"}, "image": [{"#text": "https://lastfm.freetls.fastly.net/i/u/34s/2a96cbd8b46e442fc41c2b86b821562f.png", "size": "small"}, {"#text": "https://lastfm.freetls.fastly.net/i/u/64s/2a96cbd8b46e442fc41c2b86b821562f.png", "size": "medium"}, {"#text": "https://lastfm.freetls.fastly.net/i/u/174s/2a96cbd8b46e442fc41c2b86b821562f.png", "size": "large"}, {"#text": "https://lastfm.freetls.fastly.net/i/u/300x300/2a96cbd8b46e442fc41c2b86b821562f.png", "size": "extralarge"}]}, {"name": "PERSIAN RUGS", "duration": "174", "playcount": "3278942", "listeners": "303655", "mbid": "43bb6a0f-30c3-4023-80b6-61402547f154", "url": "https://www.last.fm/music/PARTYNEXTDOOR/_/PERSIAN+RUGS", "streamable": {"#text": "0", "fulltrack": "0"}, "artist": {"name": "PARTYNEXTDOOR", "mbid": "f23ef341-33bd-47c1-b83c-846a78581f05", "url": "https://www.last.fm/music/PARTYNEXTDOOR"}, "image": [{"#text": "https://lastfm.freetls.fastly.net/i/u/34s/2a96cbd8b46e442fc41c2b86b821562f.png", "size": "small"}, {"#text": "https://lastfm.freetls.fastly.net/i/u/64s/2a96cbd8b46e442fc41c2b86b821562f.png", "size": "medium"}, {"#text": "https://lastfm.freetls.fastly.net/i/u/174s/2a96cbd8b46e442fc41c2b86b821562f.png", "size": "large"}, {"#text": "https://lastfm.freetls.fastly.net/i/u/300x300/2a96cbd8b46e442fc41c2b86b821562f.png", "size": "extralarge"}]}, {"name": "No Wind Resistance!", "duration": "198", "playcount": "2737465", "listeners": "308766", "mbid": "2456d87a-6787-41ed-b399-41beed1807cf", "url": "https://www.last.fm/music/Kinneret/_/No+Wind+Resistance%21", "streamable": {"#text": "0", "fulltrack": "0"}, "artist": {"name": "Kinneret", "mbid": "707bbfac-0fe4-4c46-abb3-8f7ff5602d8e", "url": "https://www.last.fm/music/Kinneret"}, "image": [{"#text": "https://lastfm.freetls.fastly.net/i/u/34s/2a96cbd8b46e442fc41c2b86b821562f.png", "size": "small"}, {"#text": "https://lastfm.freetls.fastly.net/i/u/64s/2a96cbd8b46e442fc41c2b86b821562f.png", "size": "medium"}, {"#text": "https://lastfm.freetls.fastly.net/i/u/174s/2a96cbd8b46e442fc41c2b86b821562f.png", "size": "large"}, {"#text": "https://lastfm.freetls.fastly.net/i/u/300x300/2a96cbd8b46e442fc41c2b86b821562f.png", "size": "extralarge"}]}, {"name": "I Feel Like I'm Drowning", "duration": "185", "playcount": "4331148", "listeners": "564260", "mbid": "ba8ffa3b-9a40-44dd-a7e3-013fcd2ded8e", "url": "https://www.last.fm/music/Two+Feet/_/I+Feel+Like+I%27m+Drowning", "streamable": {"#text": "0", "fulltrack": "0"}, "artist": {"name": "Two Feet", "mbid": "dffd8e78-761d-4997-9d73-24983e29a6dc", "url": "https://www.last.fm/music/Two+Feet"}, "image": [{"#text": "https://lastfm.freetls.fastly.net/i/u/34s/2a96cbd8b46e442fc41c2b86b821562f.png", "size": "small"}, {"#text": "https://lastfm.freetls.fastly.net/i/u/64s/2a96cbd8b46e442fc41c2b86b821562f.png", "size": "medium"}, {"#text": "https://lastfm.freetls.fastly.net/i/u/174s/2a96cbd8b46e442fc41c2b86b821562f.png", "size": "large"}, {"#text": "https://lastfm.freetls.fastly.net/i/u/300x300/2a96cbd8b46e442fc41c2b86b821562f.png", "size": "extralarge"}]}, {"name": "Christmas Magic", "duration": "190", "playcount": "120010", "listeners": "36528", "mbid": "93ef187e-79fc-4054-a22d-70e0955f109c", "url": "https://www.last.fm/music/Laufey/_/Christmas+Magic", "streamable": {"#text": "0", "fulltrack": "0"}, "artist": {"name": "Laufey", "mbid": "21a89505-10a9-4ac0-8388-833bc07b9f86", "url": "https://www.last.fm/music/Laufey"}, "image": [{"#text": "https://lastfm.freetls.fastly.net/i/u/34s/2a96cbd8b46e442fc41c2b86b821562f.png", "size": "small"}, {"#text": "https://lastfm.freetls.fastly.net/i/u/64s/2a96cbd8b46e442fc41c2b86b821562f.png", "size": "medium"}, {"#text": "https://lastfm.freetls.fastly.net/i/u/174s/2a96cbd8b46e442fc41c2b86b821562f.png", "size": "large"}, {"#text": "https://lastfm.freetls.fastly.net/i/u/300x300/2a96cbd8b46e442fc41c2b86b821562f.png", "size": "extralarge"}]}, {"name": "Jump", "duration": "0", "playcount": "3187780", "listeners": "394501", "url": "https://www.last.fm/music/Tyla/_/Jump", "streamable": {"#text": "0", "fulltrack": "0"}, "artist": {"name": "Tyla", "url": "https://www.last.fm/music/Tyla"}, "image": [{"#text": "https://lastfm.freetls.fastly.net/i/u/34s/2a96cbd8b46e442fc41c2b86b821562f.png", "size": "small"}, {"#text": "https://lastfm.freetls.fastly.net/i/u/64s/2a96cbd8b46e442fc41c2b86b821562f.png", "size": "medium"}, {"#text": "https://lastfm.freetls.fastly.net/i/u/174s/2a96cbd8b46e442fc41c2b86b821562f.png", "size": "large"}, {"#text": "https://lastfm.freetls.fastly.net/i/u/300x300/2a96cbd8b46e442fc41c2b86b821562f.png", "size": "extralarge"}]}, {"name": "Henry, come on", "duration": "317", "playcount": "4448976", "listeners": "323527", "mbid": "c01faa12-f378-4534-9c6d-f33ac5bfe342", "url": "https://www.last.fm/music/Lana+Del+Rey/_/Henry,+come+on", "streamable": {"#text": "0", "fulltrack": "0"}, "artist": {"name": "Lana Del Rey", "mbid": "b7539c32-53e7-4908-bda3-81449c367da6", "url": "https://www.last.fm/music/Lana+Del+Rey"}, "image": [{"#text": "https://lastfm.freetls.fastly.net/i/u/34s/2a96cbd8b46e442fc41c2b86b821562f.png", "size": "small"}, {"#text": "https://lastfm.freetls.fastly.net/i/u/64s/2a96cbd8b46e442fc41c2b86b821562f.png", "size": "medium"}, {"#text": "https://lastfm.freetls.fastly.net/i/u/174s/2a96cbd8b46e442fc41c2b86b821562f.png", "size": "large"}, {"#text": "https://lastfm.freetls.fastly.net/i/u/300x300/2a96cbd8b46e442fc41c2b86b821562f.png", "size": "extralarge"}]}, {"name": "Gwen Everest", "duration": "184", "playcount": "3040920", "listeners": "337437", "mbid": "ce101ca5-61e0-4e6b-a031-e774b7db5f4f", "url": "https://www.last.fm/music/Panchiko/_/Gwen+Everest", "streamable": {"#text": "0", "fulltrack": "0"}, "artist": {"name": "Panchiko", "mbid": "8f64d6ea-3f6c-408c-b2e0-e5334b28dae9", "url": "https://www.last.fm/music/Panchiko"}, "image": [{"#text": "https://lastfm.freetls.fastly.net/i/u/34s/2a96cbd8b46e442fc41c2b86b821562f.png", "size": "small"}, {"#text": "https://lastfm.freetls.fastly.net/i/u/64s/2a96cbd8b46e442fc41c2b86b821562f.png", "size": "medium"}, {"#text": "https://lastfm.freetls.fastly.net/i/u/174s/2a96cbd8b46e442fc41c2b86b821562f.png", "size": "large"}, {"#text": "https://lastfm.freetls.fastly.net/i/u/300x300/2a96cbd8b46e442fc41c2b86b821562f.png", "size": "extralarge"}]}, {"name": "Doja", "duration": "90", "playcount": "7158581", "listeners": "651838", "mbid": "1126feb5-85fd-4bf8-aa2b-676ee7177590", "url": "https://www.last.fm/music/Central+Cee/_/Doja", "streamable": {"#text": "0", "fulltrack": "0"}, "artist": {"name": "Central Cee", "mbid": "b0337af1-8d93-4671-b6c9-ba306bf942bf", "url": "https://www.last.fm/music/Central+Cee"}, "image": [{"#text": "https://lastfm.freetls.fastly.net/i/u/34s/2a96cbd8b46e442fc41c2b86b821562f.png", "size": "small"}, {"#text": "https://lastfm.freetls.fastly.net/i/u/64s/2a96cbd8b46e442fc41c2b86b821562f.png", "size": "medium"}, {"#text": "https://lastfm.freetls.fastly.net/i/u/174s/2a96cbd8b46e442fc41c2b86b821562f.png", "size": "large"}, {"#text": "https://lastfm.freetls.fastly.net/i/u/300x300/2a96cbd8b46e442fc41c2b86b821562f.png", "size": "extralarge"}]}, {"name": "\u3057\u304b\u3070\u306d\u306e\u8e0a\u308a", "duration": "228", "playcount": "2287071", "listeners": "266801", "mbid": "1bd77d8e-38d4-4d48-b5fb-b14ec4877716", "url": "https://www.last.fm/music/Kikuo/_/%E3%81%97%E3%81%8B%E3%81%B0%E3%81%AD%E3%81%AE%E8%B8%8A%E3%82%8A", "streamable": {"#text": "0", "fulltrack": "0"}, "artist": {"name": "Kikuo", "mbid": "23987750-a64d-4241-a147-2213890464a2", "url": "https://www.last.fm/music/Kikuo"}, "image": [{"#text": "https://lastfm.freetls.fastly.net/i/u/34s/2a96cbd8b46e442fc41c2b86b821562f.png", "size": "small"}, {"#text": "https://lastfm.freetls.fastly.net/i/u/64s/2a96cbd8b46e442fc41c2b86b821562f.png", "size": "medium"}, {"#text": "https://lastfm.freetls.fastly.net/i/u/174s/2a96cbd8b46e442fc41c2b86b821562f.png", "size": "large"}, {"#text": "https://lastfm.freetls.fastly.net/i/u/300x300/2a96cbd8b46e442fc41c2b86b821562f.png", "size": "extralarge"}]}, {"name": "In My Place", "duration": "228", "playcount": "12375941", "listeners": "1585155", "url": "https://www.last.fm/music/Coldplay/_/In+My+Place", "streamable": {"#text": "0", "fulltrack": "0"}, "artist": {"name": "Coldplay", "mbid": "cc197bad-dc9c-440d-a5b5-d52ba2e14234", "url": "https://www.last.fm/music/Coldplay"}, "image": [{"#text": "https://lastfm.freetls.fastly.net/i/u/34s/2a96cbd8b46e442fc41c2b86b821562f.png", "size": "small"}, {"#text": "https://lastfm.freetls.fastly.net/i/u/64s/2a96cbd8b46e442fc41c2b86b821562f.png", "size": "medium"}, {"#text": "https://lastfm.freetls.fastly.net/i/u/174s/2a96cbd8b46e442fc41c2b86b821562f.png", "size": "large"}, {"#text": "https://lastfm.freetls.fastly.net/i/u/300x300/2a96cbd8b46e442fc41c2b86b821562f.png", "size": "extralarge"}]}, {"name": "Tired of Being Alone", "duration": "168", "playcount": "3746029", "listeners": "698097", "mbid": "695f4ff7-b1cc-44ee-a0d9-5d26f7dc79c6", "url": "https://www.last.fm/music/Al+Green/_/Tired+of+Being+Alone", "streamable": {"#text": "0", "fulltrack": "0"}, "artist": {"name": "Al Green", "mbid": "fb7272ba-f130-4f0a-934d-6eeea4c18c9a", "url": "https://www.last.fm/music/Al+Green"}, "image": [{"#text": "https://lastfm.freetls.fastly.net/i/u/34s/2a96cbd8b46e442fc41c2b86b821562f.png", "size": "small"}, {"#text": "https://lastfm.freetls.fastly.net/i/u/64s/2a96cbd8b46e442fc41c2b86b821562f.png", "size": "medium"}, {"#text": "https://lastfm.freetls.fastly.net/i/u/174s/2a96cbd8b46e442fc41c2b86b821562f.png", "size": "large"}, {"#text": "https://lastfm.freetls.fastly.net/i/u/300x300/2a96cbd8b46e442fc41c2b86b821562f.png", "size": "extralarge"}]}, {"name": "Pale Moonlight", "duration": "220", "playcount": "733994", "listeners": "76250", "mbid": "7616d73a-d485-4852-abf6-6280f78b6c62", "url": "https://www.last.fm/music/Dayseeker/_/Pale+Moonlight", "streamable": {"#text": "0", "fulltrack": "0"}, "artist": {"name": "Dayseeker", "mbid": "d9a9b6aa-c5c5-40dc-95ec-0bff029245c0", "url": "https://www.last.fm/music/Dayseeker"}, "image": [{"#text": "https://lastfm.freetls.fastly.net/i/u/34s/2a96cbd8b46e442fc41c2b86b821562f.png", "size": "small"}, {"#text": "https://lastfm.freetls.fastly.net/i/u/64s/2a96cbd8b46e442fc41c2b86b821562f.png", "size": "medium"}, {"#text": "https://lastfm.freetls.fastly.net/i/u/174s/2a96cbd8b46e442fc41c2b86b821562f.png", "size": "large"}, {"#text": "https://lastfm.freetls.fastly.net/i/u/300x300/2a96cbd8b46e442fc41c2b86b821562f.png", "size": "extralarge"}]}, {"name": "Dreams Tonite", "duration": "196", "playcount": "5990290", "listeners": "566748", "mbid": "62d151f7-7639-470b-909b-7cb2c2b603d4", "url": "https://www.last.fm/music/Alvvays/_/Dreams+Tonite", "streamable": {"#text": "0", "fulltrack": "0"}, "artist": {"name": "Alvvays", "mbid": "99450990-b24e-4132-bb68-235f8c3e2564", "url": "https://www.last.fm/music/Alvvays"}, "image": [{"#text": "https://lastfm.freetls.fastly.net/i/u/34s/2a96cbd8b46e442fc41c2b86b821562f.png", "size": "small"}, {"#text": "https://lastfm.freetls.fastly.net/i/u/64s/2a96cbd8b46e442fc41c2b86b821562f.png", "size": "medium"}, {"#text": "https://lastfm.freetls.fastly.net/i/u/174s/2a96cbd8b46e442fc41c2b86b821562f.png", "size": "large"}, {"#text": "https://lastfm.freetls.fastly.net/i/u/300x300/2a96cbd8b46e442fc41c2b86b821562f.png", "size": "extralarge"}]}, {"name": "The Worst In Me", "duration": "229", "playcount": "2575076", "listeners": "206918", "mbid": "a12e087c-76f4-4c0b-a9a8-ac656d23b77b", "url": "https://www.last.fm/music/Bad+Omens/_/The+Worst+In+Me", "streamable": {"#text": "0", "fulltrack": "0"}, "artist": {"name": "Bad Omens", "mbid": "8834d8b5-72a4-4a6e-9d35-3a041b8579fa", "url": "https://www.last.fm/music/Bad+Omens"}, "image": [{"#text": "https://lastfm.freetls.fastly.net/i/u/34s/2a96cbd8b46e442fc41c2b86b821562f.png", "size": "small"}, {"#text": "https://lastfm.freetls.fastly.net/i/u/64s/2a96cbd8b46e442fc41c2b86b821562f.png", "size": "medium"}, {"#text": "https://lastfm.freetls.fastly.net/i/u/174s/2a96cbd8b46e442fc41c2b86b821562f.png", "size": "large"}, {"#text": "https://lastfm.freetls.fastly.net/i/u/300x300/2a96cbd8b46e442fc41c2b86b821562f.png", "size": "extralarge"}]}, {"name": "WHO? WHAT!", "duration": "0", "playcount": "4953887", "listeners": "456195", "url": "https://www.last.fm/music/Travis+Scott/_/WHO%3F+WHAT%21", "streamable": {"#text": "0", "fulltrack": "0"}, "artist": {"name": "Travis Scott", "mbid": "e4a51f17-a57b-47b1-b37b-f552d0f8e9e6", "url": "https://www.last.fm/music/Travis+Scott"}, "image": [{"#text": "https://lastfm.freetls.fastly.net/i/u/34s/2a96cbd8b46e442fc41c2b86b821562f.png", "size": "small"}, {"#text": "https://lastfm.freetls.fastly.net/i/u/64s/2a96cbd8b46e442fc41c2b86b821562f.png", "size": "medium"}, {"#text": "https://lastfm.freetls.fastly.net/i/u/174s/2a96cbd8b46e442fc41c2b86b821562f.png", "size": "large"}, {"#text": "https://lastfm.freetls.fastly.net/i/u/300x300/2a96cbd8b46e442fc41c2b86b821562f.png", "size": "extralarge"}]}, {"name": "Strange", "duration": "261", "playcount": "3277945", "listeners": "416753", "mbid": "dff5a5c3-40e5-4a7f-8c13-5a020382da86", "url": "https://www.last.fm/music/Celeste/_/Strange", "streamable": {"#text": "0", "fulltrack": "0"}, "artist": {"name": "Celeste", "mbid": "9b315250-d1b7-4166-bfc2-610dc9814d57", "url": "https://www.last.fm/music/Celeste"}, "image": [{"#text": "https://lastfm.freetls.fastly.net/i/u/34s/2a96cbd8b46e442fc41c2b86b821562f.png", "size": "small"}, {"#text": "https://lastfm.freetls.fastly.net/i/u/64s/2a96cbd8b46e442fc41c2b86b821562f.png", "size": "medium"}, {"#text": "https://lastfm.freetls.fastly.net/i/u/174s/2a96cbd8b46e442fc41c2b86b821562f.png", "size": "large"}, {"#text": "https://lastfm.freetls.fastly.net/i/u/300x300/2a96cbd8b46e442fc41c2b86b821562f.png", "size": "extralarge"}]}, {"name": "Fight or Flight", "duration": "172", "playcount": "4134912", "listeners": "348047", "mbid": "0fdc97c5-abe4-47f4-88d6-c88604ab7ca2", "url": "https://www.last.fm/music/Conan+Gray/_/Fight+or+Flight", "streamable": {"#text": "0", "fulltrack": "0"}, "artist": {"name": "Conan Gray", "mbid": "850a8b03-98a7-4fd3-afbd-5e5520b4ef5f", "url": "https://www.last.fm/music/Conan+Gray"}, "image": [{"#text": "https://lastfm.freetls.fastly.net/i/u/34s/2a96cbd8b46e442fc41c2b86b821562f.png", "size": "small"}, {"#text": "https://lastfm.freetls.fastly.net/i/u/64s/2a96cbd8b46e442fc41c2b86b821562f.png", "size": "medium"}, {"#text": "https://lastfm.freetls.fastly.net/i/u/174s/2a96cbd8b46e442fc41c2b86b821562f.png", "size": "large"}, {"#text": "https://lastfm.freetls.fastly.net/i/u/300x300/2a96cbd8b46e442fc41c2b86b821562f.png", "size": "extralarge"}]}, {"name": "Sugar", "duration": "177", "playcount": "4423281", "listeners": "521359", "mbid": "176b9a82-003c-4e3c-9397-0fd917b9fab4", "url": "https://www.last.fm/music/Men+I+Trust/_/Sugar", "streamable": {"#text": "0", "fulltrack": "0"}, "artist": {"name": "Men I Trust", "mbid": "25ab7547-a4d2-480b-b028-c7f3497bc858", "url": "https://www.last.fm/music/Men+I+Trust"}, "image": [{"#text": "https://lastfm.freetls.fastly.net/i/u/34s/2a96cbd8b46e442fc41c2b86b821562f.png", "size": "small"}, {"#text": "https://lastfm.freetls.fastly.net/i/u/64s/2a96cbd8b46e442fc41c2b86b821562f.png", "size": "medium"}, {"#text": "https://lastfm.freetls.fastly.net/i/u/174s/2a96cbd8b46e442fc41c2b86b821562f.png", "size": "large"}, {"#text": "https://lastfm.freetls.fastly.net/i/u/300x300/2a96cbd8b46e442fc41c2b86b821562f.png", "size": "extralarge"}]}, {"name": "Moral of the Story", "duration": "201", "playcount": "5984742", "listeners": "677646", "mbid": "024643fc-6010-44a6-a55a-fa8a9b1342cc", "url": "https://www.last.fm/music/Ashe/_/Moral+of+the+Story", "streamable": {"#text": "0", "fulltrack": "0"}, "artist": {"name": "Ashe", "mbid": "36086094-c2a4-49b9-8572-0fbf12fc3409", "url": "https://www.last.fm/music/Ashe"}, "image": [{"#text": "https://lastfm.freetls.fastly.net/i/u/34s/2a96cbd8b46e442fc41c2b86b821562f.png", "size": "small"}, {"#text": "https://lastfm.freetls.fastly.net/i/u/64s/2a96cbd8b46e442fc41c2b86b821562f.png", "size": "medium"}, {"#text": "https://lastfm.freetls.fastly.net/i/u/174s/2a96cbd8b46e442fc41c2b86b821562f.png", "size": "large"}, {"#text": "https://lastfm.freetls.fastly.net/i/u/300x300/2a96cbd8b46e442fc41c2b86b821562f.png", "size": "extralarge"}]}, {"name": "Talk Show Host", "duration": "256", "playcount": "5410810", "listeners": "693882", "url": "https://www.last.fm/music/Radiohead/_/Talk+Show+Host", "streamable": {"#text": "0", "fulltrack": "0"}, "artist": {"name": "Radiohead", "mbid": "a74b1b7f-71a5-4011-9441-d0b5e4122711", "url": "https://www.last.fm/music/Radiohead"}, "image": [{"#text": "https://lastfm.freetls.fastly.net/i/u/34s/2a96cbd8b46e442fc41c2b86b821562f.png", "size": "small"}, {"#text": "https://lastfm.freetls.fastly.net/i/u/64s/2a96cbd8b46e442fc41c2b86b821562f.png", "size": "medium"}, {"#text": "https://lastfm.freetls.fastly.net/i/u/174s/2a96cbd8b46e442fc41c2b86b821562f.png", "size": "large"}, {"#text": "https://lastfm.freetls.fastly.net/i/u/300x300/2a96cbd8b46e442fc41c2b86b821562f.png", "size": "extralarge"}]}, {"name": "Only Shallow", "duration": "240", "playcount": "10366024", "listeners": "1030651", "mbid": "57d083c7-937f-4e45-9509-a51aff157590", "url": "https://www.last.fm/music/my+bloody+valentine/_/Only+Shallow", "streamable": {"#text": "0", "fulltrack": "0"}, "artist": {"name": "my bloody valentine", "url": "https://www.last.fm/music/my+bloody+valentine"}, "image": [{"#text": "https://lastfm.freetls.fastly.net/i/u/34s/2a96cbd8b46e442fc41c2b86b821562f.png", "size": "small"}, {"#text": "https://lastfm.freetls.fastly.net/i/u/64s/2a96cbd8b46e442fc41c2b86b821562f.png", "size": "medium"}, {"#text": "https://lastfm.freetls.fastly.net/i/u/174s/2a96cbd8b46e442fc41c2b86b821562f.png", "size": "large"}, {"#text": "https://lastfm.freetls.fastly.net/i/u/300x300/2a96cbd8b46e442fc41c2b86b821562f.png", "size": "extralarge"}]}, {"name": "Class Fight", "duration": "161", "playcount": "3923045", "listeners": "415204", "mbid": "01a9478b-10f4-45fc-92ea-8de47f491d4d", "url": "https://www.last.fm/music/Melanie+Martinez/_/Class+Fight", "streamable": {"#text": "0", "fulltrack": "0"}, "artist": {"name": "Melanie Martinez", "mbid": "aaed1746-ea00-4cb4-9273-88b34e148991", "url": "https://www.last.fm/music/Melanie+Martinez"}, "image": [{"#text": "https://lastfm.freetls.fastly.net/i/u/34s/2a96cbd8b46e442fc41c2b86b821562f.png", "size": "small"}, {"#text": "https://lastfm.freetls.fastly.net/i/u/64s/2a96cbd8b46e442fc41c2b86b821562f.png", "size": "medium"}, {"#text": "https://lastfm.freetls.fastly.net/i/u/174s/2a96cbd8b46e442fc41c2b86b821562f.png", "size": "large"}, {"#text": "https://lastfm.freetls.fastly.net/i/u/300x300/2a96cbd8b46e442fc41c2b86b821562f.png", "size": "extralarge"}]}], "@attr": {"page": "154", "perPage": "50", "totalPages": "18978371", "total": "948918503"}}}