{"toptags": {"tag": [{"count": 100, "name": "alternative R&B", "url": "https://www.last.fm/tag/alternative+R&B"}, {"count": 25, "name": "metal", "url": "https://www.last.fm/tag/metal"}, {"count": 16, "name": "soul", "url": "https://www.last.fm/tag/soul"}, {"count": 16, "name": "Progressive", "url": "https://www.last.fm/tag/Progressive"}, {"count": 8, "name": "Progressive metal", "url": "https://www.last.fm/tag/Progressive+metal"}, {"count": 8, "name": "alt-pop", "url": "https://www.last.fm/tag/alt-pop"}, {"count": 8, "name": "art pop", "url": "https://www.last.fm/tag/art+pop"}, {"count": 2, "name": "possible for liberals to deal with", "url": "https://www.last.fm/tag/possible+for+liberals+to+deal+with"}, {"count": 2, "name": "DJENT", "url": "https://www.last.fm/tag/DJENT"}], "@attr": {"artist": "Sleep Token", "track": "Aqua Regia"}}}