{"toptags": {"tag": [{"count": 100, "name": "k-pop", "url": "https://www.last.fm/tag/k-pop"}, {"count": 56, "name": "pop", "url": "https://www.last.fm/tag/pop"}, {"count": 37, "name": "Hip-Hop", "url": "https://www.last.fm/tag/Hip-Hop"}, {"count": 37, "name": "hip hop", "url": "https://www.last.fm/tag/hip+hop"}, {"count": 19, "name": "pop rap", "url": "https://www.last.fm/tag/pop+rap"}, {"count": 8, "name": "Korean", "url": "https://www.last.fm/tag/Korean"}, {"count": 8, "name": "Kpop", "url": "https://www.last.fm/tag/Kpop"}, {"count": 3, "name": "trap", "url": "https://www.last.fm/tag/trap"}, {"count": 1, "name": "Empowering", "url": "https://www.last.fm/tag/Empowering"}, {"count": 1, "name": "rap", "url": "https://www.last.fm/tag/rap"}], "@attr": {"artist": "BLACKPINK", "track": "Typa Girl"}}}