{"toptags": {"tag": [{"count": 100, "name": "brazilian rock", "url": "https://www.last.fm/tag/brazilian+rock"}, {"count": 100, "name": "brasil", "url": "https://www.last.fm/tag/brasil"}, {"count": 66, "name": "cute songs", "url": "https://www.last.fm/tag/cute+songs"}, {"count": 66, "name": "mpb", "url": "https://www.last.fm/tag/mpb"}, {"count": 33, "name": "clipe", "url": "https://www.last.fm/tag/clipe"}, {"count": 33, "name": "historia", "url": "https://www.last.fm/tag/historia"}, {"count": 33, "name": "melancolia", "url": "https://www.last.fm/tag/melancolia"}, {"count": 10, "name": "me identifico", "url": "https://www.last.fm/tag/me+identifico"}, {"count": 10, "name": "2010s", "url": "https://www.last.fm/tag/2010s"}, {"count": 10, "name": "if this was a pokemon i would catch it", "url": "https://www.last.fm/tag/if+this+was+a+pokemon+i+would+catch+it"}], "@attr": {"artist": "Pequeno Cidad\u00e3o", "track": "O Sol e a Lua"}}}