{"toptags": {"tag": [{"count": 100, "name": "sing along", "url": "https://www.last.fm/tag/sing+along"}, {"count": 100, "name": "catchy", "url": "https://www.last.fm/tag/catchy"}, {"count": 66, "name": "dad rock", "url": "https://www.last.fm/tag/dad+rock"}, {"count": 66, "name": "fundamental", "url": "https://www.last.fm/tag/fundamental"}, {"count": 33, "name": "engaging", "url": "https://www.last.fm/tag/engaging"}, {"count": 33, "name": "good chorus", "url": "https://www.last.fm/tag/good+chorus"}], "@attr": {"artist": "Metallica", "track": "Nothing Else Matters - Remastered 2021"}}}