{"toptags": {"tag": [{"count": 100, "name": "kendrick lamar", "url": "https://www.last.fm/tag/kendrick+lamar"}, {"count": 44, "name": "yacht rock", "url": "https://www.last.fm/tag/yacht+rock"}, {"count": 29, "name": "jazz fusion", "url": "https://www.last.fm/tag/jazz+fusion"}, {"count": 7, "name": "soul", "url": "https://www.last.fm/tag/soul"}, {"count": 4, "name": "sweet", "url": "https://www.last.fm/tag/sweet"}, {"count": 4, "name": "Neo-Soul", "url": "https://www.last.fm/tag/Neo-Soul"}, {"count": 4, "name": "bass", "url": "https://www.last.fm/tag/bass"}, {"count": 1, "name": "Psychedelic Soul", "url": "https://www.last.fm/tag/Psychedelic+Soul"}, {"count": 1, "name": "west coast hip hop", "url": "https://www.last.fm/tag/west+coast+hip+hop"}, {"count": 1, "name": "Conscious Hip Hop", "url": "https://www.last.fm/tag/Conscious+Hip+Hop"}], "@attr": {"artist": "Thundercat", "track": "Walk on By"}}}