{"toptags": {"tag": [{"count": 100, "name": "Korean", "url": "https://www.last.fm/tag/Korean"}, {"count": 100, "name": "hip hop", "url": "https://www.last.fm/tag/hip+hop"}, {"count": 66, "name": "Kpop", "url": "https://www.last.fm/tag/Kpop"}, {"count": 66, "name": "alternative hip hop", "url": "https://www.last.fm/tag/alternative+hip+hop"}, {"count": 33, "name": "k hip hop", "url": "https://www.last.fm/tag/k+hip+hop"}, {"count": 33, "name": "wb yoongi", "url": "https://www.last.fm/tag/wb+yoongi"}], "@attr": {"artist": "Agust D", "track": "Moonlight"}}}