{"toptags": {"tag": [{"count": 100, "name": "rnb", "url": "https://www.last.fm/tag/rnb"}, {"count": 64, "name": "trap", "url": "https://www.last.fm/tag/trap"}, {"count": 24, "name": "soul", "url": "https://www.last.fm/tag/soul"}, {"count": 11, "name": "urban", "url": "https://www.last.fm/tag/urban"}, {"count": 1, "name": "pop", "url": "https://www.last.fm/tag/pop"}, {"count": 1, "name": "electropop", "url": "https://www.last.fm/tag/electropop"}, {"count": 1, "name": "electronic", "url": "https://www.last.fm/tag/electronic"}, {"count": 1, "name": "UK Garage", "url": "https://www.last.fm/tag/UK+Garage"}, {"count": 1, "name": "Hip-Hop", "url": "https://www.last.fm/tag/Hip-Hop"}, {"count": 1, "name": "sad", "url": "https://www.last.fm/tag/sad"}], "@attr": {"artist": "The Weeknd", "track": "Wasted Times"}}}