{"toptags": {"tag": [{"count": 100, "name": "blue side", "url": "https://www.last.fm/tag/blue+side"}, {"count": 100, "name": "airplane", "url": "https://www.last.fm/tag/airplane"}, {"count": 66, "name": "More y Arson", "url": "https://www.last.fm/tag/More+y+Arson"}, {"count": 24, "name": "Lock unlock", "url": "https://www.last.fm/tag/Lock+unlock"}, {"count": 1, "name": "MORE", "url": "https://www.last.fm/tag/MORE"}, {"count": 1, "name": "arson", "url": "https://www.last.fm/tag/arson"}, {"count": 1, "name": "disco funk", "url": "https://www.last.fm/tag/disco+funk"}], "@attr": {"artist": "j-hope", "track": "lock / unlock (with benny blanco & Nile Rodgers)"}}}