{"toptags": {"tag": [{"count": 100, "name": "Drum and bass", "url": "https://www.last.fm/tag/Drum+and+bass"}, {"count": 16, "name": "dubstep", "url": "https://www.last.fm/tag/dubstep"}, {"count": 11, "name": "EDM", "url": "https://www.last.fm/tag/EDM"}, {"count": 3, "name": "House", "url": "https://www.last.fm/tag/House"}, {"count": 1, "name": "dnb", "url": "https://www.last.fm/tag/dnb"}, {"count": 1, "name": "dance", "url": "https://www.last.fm/tag/dance"}, {"count": 1, "name": "electronic", "url": "https://www.last.fm/tag/electronic"}, {"count": 1, "name": "drop", "url": "https://www.last.fm/tag/drop"}, {"count": 1, "name": "Liquid", "url": "https://www.last.fm/tag/Liquid"}, {"count": 1, "name": "Acapella", "url": "https://www.last.fm/tag/Acapella"}], "@attr": {"artist": "Fred again..", "track": "leavemealone"}}}