{"toptags": {"tag": [{"count": 100, "name": "pop", "url": "https://www.last.fm/tag/pop"}, {"count": 33, "name": "rnb", "url": "https://www.last.fm/tag/rnb"}, {"count": 22, "name": "future", "url": "https://www.last.fm/tag/future"}, {"count": 22, "name": "pop rap", "url": "https://www.last.fm/tag/pop+rap"}, {"count": 11, "name": "Ed Sheeran", "url": "https://www.last.fm/tag/Ed+Sheeran"}, {"count": 6, "name": "power pop", "url": "https://www.last.fm/tag/power+pop"}, {"count": 6, "name": "rap", "url": "https://www.last.fm/tag/rap"}, {"count": 2, "name": "Hip-Hop", "url": "https://www.last.fm/tag/Hip-Hop"}, {"count": 1, "name": "female vocalist", "url": "https://www.last.fm/tag/female+vocalist"}, {"count": 1, "name": "electropop", "url": "https://www.last.fm/tag/electropop"}], "@attr": {"artist": "Taylor Swift", "track": "End Game"}}}