{"toptags": {"tag": [{"count": 100, "name": "my top songs", "url": "https://www.last.fm/tag/my+top+songs"}, {"count": 25, "name": "dub", "url": "https://www.last.fm/tag/dub"}, {"count": 16, "name": "indie", "url": "https://www.last.fm/tag/indie"}, {"count": 16, "name": "pop", "url": "https://www.last.fm/tag/pop"}, {"count": 8, "name": "sad", "url": "https://www.last.fm/tag/sad"}, {"count": 8, "name": "Soundtrack", "url": "https://www.last.fm/tag/Soundtrack"}, {"count": 8, "name": "Progressive rock", "url": "https://www.last.fm/tag/Progressive+rock"}, {"count": 3, "name": "goosebumps", "url": "https://www.last.fm/tag/goosebumps"}, {"count": 3, "name": "cinematic", "url": "https://www.last.fm/tag/cinematic"}, {"count": 3, "name": "chill", "url": "https://www.last.fm/tag/chill"}], "@attr": {"artist": "Ashe", "track": "Moral of the Story"}}}