{"toptags": {"tag": [{"count": 100, "name": "jazz", "url": "https://www.last.fm/tag/jazz"}, {"count": 100, "name": "folk", "url": "https://www.last.fm/tag/folk"}, {"count": 66, "name": "piano", "url": "https://www.last.fm/tag/piano"}, {"count": 66, "name": "pop", "url": "https://www.last.fm/tag/pop"}, {"count": 33, "name": "vocal", "url": "https://www.last.fm/tag/vocal"}, {"count": 33, "name": "Avant-Garde", "url": "https://www.last.fm/tag/Avant-Garde"}, {"count": 33, "name": "beats", "url": "https://www.last.fm/tag/beats"}, {"count": 10, "name": "viola", "url": "https://www.last.fm/tag/viola"}, {"count": 10, "name": "violin", "url": "https://www.last.fm/tag/violin"}, {"count": 10, "name": "baroque pop", "url": "https://www.last.fm/tag/baroque+pop"}], "@attr": {"artist": "ROSAL\u00cdA", "track": "Divinize"}}}