{"toptags": {"tag": [{"count": 100, "name": "synthpop", "url": "https://www.last.fm/tag/synthpop"}, {"count": 79, "name": "dance-pop", "url": "https://www.last.fm/tag/dance-pop"}, {"count": 13, "name": "alternative dance", "url": "https://www.last.fm/tag/alternative+dance"}, {"count": 13, "name": "nu-disco", "url": "https://www.last.fm/tag/nu-disco"}, {"count": 7, "name": "chillwave", "url": "https://www.last.fm/tag/chillwave"}, {"count": 4, "name": "electronic", "url": "https://www.last.fm/tag/electronic"}, {"count": 4, "name": "Neo-Psychedelia", "url": "https://www.last.fm/tag/Neo-Psychedelia"}, {"count": 1, "name": "electro-disco", "url": "https://www.last.fm/tag/electro-disco"}, {"count": 1, "name": "dance", "url": "https://www.last.fm/tag/dance"}, {"count": 1, "name": "pop", "url": "https://www.last.fm/tag/pop"}], "@attr": {"artist": "Magdalena Bay", "track": "Image"}}}