{"similartracks": {"track": [{"name": "Dynamite", "playcount": 11168510, "match": 1.0, "url": "https://www.last.fm/music/Taio+Cruz/_/Dynamite", "streamable": {"#text": "0", "fulltrack": "0"}, "duration": 202, "artist": {"name": "Taio Cruz", "mbid": "ba7d2626-38ce-4859-8495-bdb5732715c4", "url": "https://www.last.fm/music/Taio+Cruz"}, "image": [{"#text": "https://lastfm.freetls.fastly.net/i/u/34s/2a96cbd8b46e442fc41c2b86b821562f.png", "size": "small"}, {"#text": "https://lastfm.freetls.fastly.net/i/u/64s/2a96cbd8b46e442fc41c2b86b821562f.png", "size": "medium"}, {"#text": "https://lastfm.freetls.fastly.net/i/u/174s/2a96cbd8b46e442fc41c2b86b821562f.png", "size": "large"}, {"#text": "https://lastfm.freetls.fastly.net/i/u/300x300/2a96cbd8b46e442fc41c2b86b821562f.png", "size": "extralarge"}, {"#text": "https://lastfm.freetls.fastly.net/i/u/300x300/2a96cbd8b46e442fc41c2b86b821562f.png", "size": "mega"}, {"#text": "https://lastfm.freetls.fastly.net/i/u/300x300/2a96cbd8b46e442fc41c2b86b821562f.png", "size": ""}]}, {"name": "OMG (feat. will.i.am)", "playcount": 4233407, "match": 0.759002, "url": "https://www.last.fm/music/Usher/_/OMG+(feat.+will.i.am)", "streamable": {"#text": "0", "fulltrack": "0"}, "duration": 269, "artist": {"name": "Usher", "mbid": "3414d446-735a-443c-931f-10634f57e5b9", "url": "https://www.last.fm/music/Usher"}, "image": [{"#text": "https://lastfm.freetls.fastly.net/i/u/34s/2a96cbd8b46e442fc41c2b86b821562f.png", "size": "small"}, {"#text": "https://lastfm.freetls.fastly.net/i/u/64s/2a96cbd8b46e442fc41c2b86b821562f.png", "size": "medium"}, {"#text": "https://lastfm.freetls.fastly.net/i/u/174s/2a96cbd8b46e442fc41c2b86b821562f.png", "size": "large"}, {"#text": "https://lastfm.freetls.fastly.net/i/u/300x300/2a96cbd8b46e442fc41c2b86b821562f.png", "size": "extralarge"}, {"#text": "https://lastfm.freetls.fastly.net/i/u/300x300/2a96cbd8b46e442fc41c2b86b821562f.png", "size": "mega"}, {"#text": "https://lastfm.freetls.fastly.net/i/u/300x300/2a96cbd8b46e442fc41c2b86b821562f.png", "size": ""}]}, {"name": "Don't Stop the Music", "playcount": 17911150, "match": 0.7371, "url": "https://www.last.fm/music/Rihanna/_/Don%27t+Stop+the+Music", "streamable": {"#text": "0", "fulltrack": "0"}, "duration": 193, "artist": {"name": "Rihanna", "mbid": "73e5e69d-3554-40d8-8516-00cb38737a1c", "url": "https://www.last.fm/music/Rihanna"}, "image": [{"#text": "https://lastfm.freetls.fastly.net/i/u/34s/2a96cbd8b46e442fc41c2b86b821562f.png", "size": "small"}, {"#text": "https://lastfm.freetls.fastly.net/i/u/64s/2a96cbd8b46e442fc41c2b86b821562f.png", "size": "medium"}, {"#text": "https://lastfm.freetls.fastly.net/i/u/174s/2a96cbd8b46e442fc41c2b86b821562f.png", "size": "large"}, {"#text": "https://lastfm.freetls.fastly.net/i/u/300x300/2a96cbd8b46e442fc41c2b86b821562f.png", "size": "extralarge"}, {"#text": "https://lastfm.freetls.fastly.net/i/u/300x300/2a96cbd8b46e442fc41c2b86b821562f.png", "size": "mega"}, {"#text": "https://lastfm.freetls.fastly.net/i/u/300x300/2a96cbd8b46e442fc41c2b86b821562f.png", "size": ""}]}], "@attr": {"artist": "Usher", "track": "DJ Got Us Fallin' in Love (feat. Pitbull)"}}}