{"toptags": {"tag": [{"count": 100, "name": "Nu Metal", "url": "https://www.last.fm/tag/Nu+Metal"}, {"count": 66, "name": "metal", "url": "https://www.last.fm/tag/metal"}, {"count": 35, "name": "alternative metal", "url": "https://www.last.fm/tag/alternative+metal"}, {"count": 13, "name": "Slipknot", "url": "https://www.last.fm/tag/Slipknot"}, {"count": 6, "name": "Nu-metal", "url": "https://www.last.fm/tag/Nu-metal"}, {"count": 5, "name": "heavy metal", "url": "https://www.last.fm/tag/heavy+metal"}, {"count": 5, "name": "metalcore", "url": "https://www.last.fm/tag/metalcore"}, {"count": 1, "name": "hardcore", "url": "https://www.last.fm/tag/hardcore"}, {"count": 1, "name": "rock", "url": "https://www.last.fm/tag/rock"}, {"count": 1, "name": "corey taylor", "url": "https://www.last.fm/tag/corey+taylor"}], "@attr": {"artist": "Slipknot", "track": "Eyeless"}}}