{"toptags": {"tag": [{"count": 100, "name": "synthpop", "url": "https://www.last.fm/tag/synthpop"}, {"count": 100, "name": "new wave", "url": "https://www.last.fm/tag/new+wave"}, {"count": 66, "name": "alt-pop", "url": "https://www.last.fm/tag/alt-pop"}, {"count": 66, "name": "jersey club", "url": "https://www.last.fm/tag/jersey+club"}, {"count": 15, "name": "trip hop", "url": "https://www.last.fm/tag/trip+hop"}, {"count": 4, "name": "k-pop", "url": "https://www.last.fm/tag/k-pop"}, {"count": 4, "name": "pop rock", "url": "https://www.last.fm/tag/pop+rock"}, {"count": 1, "name": "Korean", "url": "https://www.last.fm/tag/Korean"}, {"count": 1, "name": "Kpop", "url": "https://www.last.fm/tag/Kpop"}, {"count": 1, "name": "contemporary rnb", "url": "https://www.last.fm/tag/contemporary+rnb"}], "@attr": {"artist": "NMIXX", "track": "Blue Valentine"}}}