{"toptags": {"tag": [{"count": 100, "name": "synth funk", "url": "https://www.last.fm/tag/synth+funk"}, {"count": 100, "name": "freestyle", "url": "https://www.last.fm/tag/freestyle"}, {"count": 37, "name": "dance-pop", "url": "https://www.last.fm/tag/dance-pop"}, {"count": 37, "name": "vie", "url": "https://www.last.fm/tag/vie"}, {"count": 19, "name": "edu e marco", "url": "https://www.last.fm/tag/edu+e+marco"}, {"count": 8, "name": "pop rap", "url": "https://www.last.fm/tag/pop+rap"}, {"count": 8, "name": "pop", "url": "https://www.last.fm/tag/pop"}, {"count": 2, "name": "minneapolis sound", "url": "https://www.last.fm/tag/minneapolis+sound"}, {"count": 2, "name": "new jack swing", "url": "https://www.last.fm/tag/new+jack+swing"}, {"count": 1, "name": "rap", "url": "https://www.last.fm/tag/rap"}], "@attr": {"artist": "Doja Cat", "track": "Jealous Type"}}}