{"toptags": {"tag": [{"count": 100, "name": "rock", "url": "https://www.last.fm/tag/rock"}, {"count": 69, "name": "alternative rock", "url": "https://www.last.fm/tag/alternative+rock"}, {"count": 29, "name": "brazilian", "url": "https://www.last.fm/tag/brazilian"}, {"count": 17, "name": "brasil", "url": "https://www.last.fm/tag/brasil"}, {"count": 8, "name": "skate music", "url": "https://www.last.fm/tag/skate+music"}, {"count": 8, "name": "cbjr", "url": "https://www.last.fm/tag/cbjr"}, {"count": 8, "name": "rock brasileiro", "url": "https://www.last.fm/tag/rock+brasileiro"}, {"count": 1, "name": "Nacional", "url": "https://www.last.fm/tag/Nacional"}, {"count": 1, "name": "nostalgia", "url": "https://www.last.fm/tag/nostalgia"}, {"count": 1, "name": "neu", "url": "https://www.last.fm/tag/neu"}], "@attr": {"artist": "Charlie Brown Jr.", "track": "Como Tudo Deve Ser"}}}