{"toptags": {"tag": [{"count": 100, "name": "indie folk", "url": "https://www.last.fm/tag/indie+folk"}, {"count": 25, "name": "japanese", "url": "https://www.last.fm/tag/japanese"}, {"count": 16, "name": "Love", "url": "https://www.last.fm/tag/Love"}, {"count": 16, "name": "singer-songwriter", "url": "https://www.last.fm/tag/singer-songwriter"}, {"count": 8, "name": "romantic", "url": "https://www.last.fm/tag/romantic"}, {"count": 8, "name": "shibuya-kei", "url": "https://www.last.fm/tag/shibuya-kei"}, {"count": 8, "name": "Bossa Nova", "url": "https://www.last.fm/tag/Bossa+Nova"}, {"count": 3, "name": "aww", "url": "https://www.last.fm/tag/aww"}, {"count": 3, "name": "sunshine pop", "url": "https://www.last.fm/tag/sunshine+pop"}, {"count": 3, "name": "Olivia", "url": "https://www.last.fm/tag/Olivia"}], "@attr": {"artist": "Lamp", "track": "For Lovers"}}}