{"toptags": {"tag": [{"count": 100, "name": "classic rock", "url": "https://www.last.fm/tag/classic+rock"}, {"count": 80, "name": "rock", "url": "https://www.last.fm/tag/rock"}, {"count": 28, "name": "dire straits", "url": "https://www.last.fm/tag/dire+straits"}, {"count": 25, "name": "guitar", "url": "https://www.last.fm/tag/guitar"}, {"count": 10, "name": "80s", "url": "https://www.last.fm/tag/80s"}, {"count": 7, "name": "blues rock", "url": "https://www.last.fm/tag/blues+rock"}, {"count": 7, "name": "70s", "url": "https://www.last.fm/tag/70s"}, {"count": 1, "name": "british", "url": "https://www.last.fm/tag/british"}, {"count": 1, "name": "Soundtrack", "url": "https://www.last.fm/tag/Soundtrack"}, {"count": 1, "name": "blues", "url": "https://www.last.fm/tag/blues"}], "@attr": {"artist": "Dire Straits", "track": "Six Blade Knife"}}}