{"toptags": {"tag": [{"count": 100, "name": "Hip-Hop", "url": "https://www.last.fm/tag/Hip-Hop"}, {"count": 100, "name": "rnb", "url": "https://www.last.fm/tag/rnb"}, {"count": 11, "name": "sex", "url": "https://www.last.fm/tag/sex"}, {"count": 11, "name": "hip hop", "url": "https://www.last.fm/tag/hip+hop"}, {"count": 5, "name": "r&b", "url": "https://www.last.fm/tag/r&b"}, {"count": 5, "name": "transante", "url": "https://www.last.fm/tag/transante"}, {"count": 1, "name": "sexy", "url": "https://www.last.fm/tag/sexy"}, {"count": 1, "name": "Pussy", "url": "https://www.last.fm/tag/Pussy"}, {"count": 1, "name": "pop", "url": "https://www.last.fm/tag/pop"}, {"count": 1, "name": "dance pop", "url": "https://www.last.fm/tag/dance+pop"}], "@attr": {"artist": "Rihanna", "track": "Sex With Me"}}}