{"similartracks": {"track": [{"name": "Church", "playcount": 4288281, "mbid": "736ec7a5-3959-46b0-bf1b-17ee10fc556d", "match": 1.0, "url": "https://www.last.fm/music/Chase+Atlantic/_/Church", "streamable": {"#text": "0", "fulltrack": "0"}, "duration": 220, "artist": {"name": "Chase Atlantic", "mbid": "ecab255c-3af3-4154-87ec-2685041ce297", "url": "https://www.last.fm/music/Chase+Atlantic"}, "image": [{"#text": "https://lastfm.freetls.fastly.net/i/u/34s/2a96cbd8b46e442fc41c2b86b821562f.png", "size": "small"}, {"#text": "https://lastfm.freetls.fastly.net/i/u/64s/2a96cbd8b46e442fc41c2b86b821562f.png", "size": "medium"}, {"#text": "https://lastfm.freetls.fastly.net/i/u/174s/2a96cbd8b46e442fc41c2b86b821562f.png", "size": "large"}, {"#text": "https://lastfm.freetls.fastly.net/i/u/300x300/2a96cbd8b46e442fc41c2b86b821562f.png", "size": "extralarge"}, {"#text": "https://lastfm.freetls.fastly.net/i/u/300x300/2a96cbd8b46e442fc41c2b86b821562f.png", "size": "mega"}, {"#text": "https://lastfm.freetls.fastly.net/i/u/300x300/2a96cbd8b46e442fc41c2b86b821562f.png", "size": ""}]}, {"name": "Into It", "playcount": 11385759, "mbid": "4a8f8f72-457f-4789-babe-35cdf38f7339", "match": 0.919477, "url": "https://www.last.fm/music/Chase+Atlantic/_/Into+It", "streamable": {"#text": "0", "fulltrack": "0"}, "duration": 196, "artist": {"name": "Chase Atlantic", "mbid": "ecab255c-3af3-4154-87ec-2685041ce297", "url": "https://www.last.fm/music/Chase+Atlantic"}, "image": [{"#text": "https://lastfm.freetls.fastly.net/i/u/34s/2a96cbd8b46e442fc41c2b86b821562f.png", "size": "small"}, {"#text": "https://lastfm.freetls.fastly.net/i/u/64s/2a96cbd8b46e442fc41c2b86b821562f.png", "size": "medium"}, {"#text": "https://lastfm.freetls.fastly.net/i/u/174s/2a96cbd8b46e442fc41c2b86b821562f.png", "size": "large"}, {"#text": "https://lastfm.freetls.fastly.net/i/u/300x300/2a96cbd8b46e442fc41c2b86b821562f.png", "size": "extralarge"}, {"#text": "https://lastfm.freetls.fastly.net/i/u/300x300/2a96cbd8b46e442fc41c2b86b821562f.png", "size": "mega"}, {"#text": "https://lastfm.freetls.fastly.net/i/u/300x300/2a96cbd8b46e442fc41c2b86b821562f.png", "size": ""}]}, {"name": "Consume (feat. Goon Des Garcons)", "playcount": 97568, "match": 0.0211046, "url": "https://www.last.fm/music/Chase+Atlantic,+GOON+DES+GARCONS%2A/_/Consume+(feat.+Goon+Des+Garcons)", "streamable": {"#text": "0", "fulltrack": "0"}, "duration": 0, "artist": {"name": "Chase Atlantic, GOON DES GARCONS*", "url": "https://www.last.fm/music/Chase+Atlantic,+GOON+DES+GARCONS%2A"}, "image": [{"#text": "", "size": "small"}, {"#text": "", "size": "medium"}, {"#text": "", "size": "large"}, {"#text": "", "size": "extralarge"}, {"#text": "", "size": "mega"}, {"#text": "", "size": ""}]}], "@attr": {"artist": "Chase Atlantic", "track": "The Walls"}}}