{"toptags": {"tag": [{"count": 100, "name": "Kpop", "url": "https://www.last.fm/tag/Kpop"}, {"count": 56, "name": "k-pop", "url": "https://www.last.fm/tag/k-pop"}, {"count": 16, "name": "2023", "url": "https://www.last.fm/tag/2023"}, {"count": 4, "name": "girl group", "url": "https://www.last.fm/tag/girl+group"}, {"count": 2, "name": "contemporary rnb", "url": "https://www.last.fm/tag/contemporary+rnb"}, {"count": 2, "name": "ive", "url": "https://www.last.fm/tag/ive"}, {"count": 2, "name": "calm", "url": "https://www.last.fm/tag/calm"}, {"count": 1, "name": "julia", "url": "https://www.last.fm/tag/julia"}, {"count": 1, "name": "colours", "url": "https://www.last.fm/tag/colours"}, {"count": 1, "name": "One of the greatest", "url": "https://www.last.fm/tag/One+of+the+greatest"}], "@attr": {"artist": "IVE", "track": "Off The Record"}}}