{"toptags": {"tag": [{"count": 100, "name": "dance", "url": "https://www.last.fm/tag/dance"}, {"count": 100, "name": "funk", "url": "https://www.last.fm/tag/funk"}, {"count": 17, "name": "phonk", "url": "https://www.last.fm/tag/phonk"}, {"count": 17, "name": "miami bass", "url": "https://www.last.fm/tag/miami+bass"}, {"count": 8, "name": "funk experimental", "url": "https://www.last.fm/tag/funk+experimental"}, {"count": 8, "name": "Anitta", "url": "https://www.last.fm/tag/Anitta"}, {"count": 8, "name": "tamborzao", "url": "https://www.last.fm/tag/tamborzao"}, {"count": 3, "name": "mega funk", "url": "https://www.last.fm/tag/mega+funk"}, {"count": 3, "name": "funk mandelao", "url": "https://www.last.fm/tag/funk+mandelao"}, {"count": 3, "name": "Latin Pop Girls", "url": "https://www.last.fm/tag/Latin+Pop+Girls"}], "@attr": {"artist": "Anitta", "track": "Savage Funk"}}}